Workbook

Sheet Strutture ricettive_raw
A1: Column1 | B1: Column2 | C1: Column3 | D1: Column4 | E1: Column5 | F1: Column6 | G1: Column7
A2: Categoria | B2: Denominazione | C2: Indirizzo | D2: Città | E2: Localita | F2: Indirizzo internet | G2: Indirizzo di posta elettronica
A3: TURISMO RURALE | B3: COUNTRY HOUSE LOCALITA' GIROFALCO | C3: Via Girfalco, 26 | D3: URBINO | F3: www.girfalco.it | G3: info@girfalco.it
A4: ALTRI ALLOGGI PRIVATI | B4: STAGNOZZI STEFANIA | C4: Via Candigliano 5 | D4: ACQUALAGNA | E4: ACQUALAGNA | G4: gigliovitto@libero.it
A5: ALTRI ALLOGGI PRIVATI | B5: GORGOLINI ALESSANDRO | C5: Via San Gregorio 9 | D5: ACQUALAGNA | E5: ACQUALAGNA | G5: ale.gorgolini@gmail.com
A6: ALBERGHI | B6: LEON D'ORO | C6: Via Flaminia 213 | D6: ACQUALAGNA | E6: ACQUALAGNA
A7: ALBERGHI | B7: ALBERGO DOMUS MARIAE | C7: viale Ezio Scaglioni 17 | D7: ACQUALAGNA | E7: ACQUALAGNA | G7: giulianaspini@gmail.com
A8: ALTRI ALLOGGI PRIVATI | B8: TORRE COLOMBARA DI FRONTINO | C8: STRADA FRONTINO 24/B | D8: ACQUALAGNA | E8: ACQUALAGNA | G8: luccardi.sandro@gmail.com
A9: BED & BREAKFAST | B9: B&B AQUILEGIA | C9: via Furlo 12 | D9: ACQUALAGNA | E9: Furlo | F9: www.aquilegiabeb.com | G9: info@aquilegiabeb.com
A10: ALLOGGI AGRITURISTICI | B10: DEL FRONTINO | C10: strada frontino 23 | D10: ACQUALAGNA | E10: ACQUALAGNA
A11: ALBERGHI | B11: LA GINESTRA | C11: via Furlo 17 | D11: ACQUALAGNA | E11: ACQUALAGNA | F11: www.ginestrafurlo.it | G11: info@ginestrafurlo.it
A12: ALBERGHI | B12: BIRRA AL POZZO | C12: via Pianacce 12 | D12: ACQUALAGNA | E12: ACQUALAGNA | F12: www.birraalpozzo.it | G12: info@birraalpozzo.it
A13: BED & BREAKFAST | B13: B&B CRISTINI CRISTINA | C13: strada frontino 23 | D13: ACQUALAGNA | E13: ACQUALAGNA | G13: cri.cristini@alice.it
A14: BED & BREAKFAST | B14: B&B MARTELLONI CESARE | C14: via pianacce 67 | D14: ACQUALAGNA | E14: ACQUALAGNA | F14: www.lalocandadellabbazia.it | G14: info@lalocandadellabbazia.it
A15: ALBERGHI | B15: ALBERGO MEUBLE' SHINE | C15: via aldo gamba 54 | D15: ACQUALAGNA | E15: ACQUALAGNA
A16: ALLOGGI AGRITURISTICI | B16: AGRITURISMO CASTELLAGO | C16: strada Castellaro 18 | D16: ACQUALAGNA | E16: ACQUALAGNA | G16: castellago@virgilio.it
A17: ALBERGHI | B17: ALBERGO ANTICO FURLO | C17: via Flaminia 66 | D17: ACQUALAGNA | E17: ACQUALAGNA | F17: www.anticofurlo.it | G17: info@anticofurlo.it
A18: TURISMO RURALE | B18: CA' GARAVANO | C18: strada Frontino 21 | D18: ACQUALAGNA | E18: ACQUALAGNA | F18: www.cagaravano.com | G18: urbini.alessandro@alice.it
A19: ALTRI ALLOGGI PRIVATI | B19: IL CONIO DI DI GIOVANNI FEDERICO | C19: strada pietralatra 1 | D19: ACQUALAGNA | E19: ACQUALAGNA
A20: ALLOGGI AGRITURISTICI | B20: AGRITURISMO I CONTI | C20: via Pieve del Colle 11 b | D20: ACQUALAGNA | E20: pieve del colle | F20: www.agriturismoiconti.it | G20: info@agriturismoiconti.it
A21: ALLOGGI AGRITURISTICI | B21: LA COLOMBARA | C21: strada Frontino 24 | D21: ACQUALAGNA
A22: ALTRI ALLOGGI PRIVATI | B22: STROPPA GIUSEPPE | C22: strada San Gregorio 12 | D22: ACQUALAGNA | E22: Acqualagna | F22: http://lapanoramicadastroppa.webstarts.com/ | G22: stroppag@libero.it
A23: ALTRI ALLOGGI PRIVATI | B23: SERAFINI GIORGIA | D23: ACQUALAGNA
A24: ALTRI ALLOGGI PRIVATI | B24: BETTI VINCENZO | C24: via Pole 69 | D24: ACQUALAGNA
A25: ALLOGGI IN AFFITTO | B25: MARCHEHOLIDAY - CASALE DEGLI ULIVI | C25: strada San Gregorio 1 | D25: ACQUALAGNA | E25: loc.Ca Donnino | F25: www.marcheholiday.it/ulivi | G25: info@marcheholiday.it
A26: AREE DI SOSTA (PLEIN AIR) | B26: AREA SOSTA CAMPER PARCO LE QUERCE | C26: via Pianacce 1 | D26: ACQUALAGNA | E26: RISERVA NATURALE STATALE GOLA DEL FURLO | F26: parcodelfurlo.it | G26: info@parcodelfurlo.it
A27: ALTRI ALLOGGI PRIVATI | B27: BACCHIOCCHI MARIA ELISA | C27: via San Gregorio 17 | D27: ACQUALAGNA | G27: remigio.battistelli@gmail.com
A28: ALTRI ALLOGGI PRIVATI | B28: MARCHETTI LORENZA | C28: via Fossato 37/b | D28: ACQUALAGNA | G28: thomas.clementi@hotmail.it
A29: BED & BREAKFAST | B29: B&B BISCUBIO | C29: via Circonvallazione 46 | D29: APECCHIO | G29: marcellamartinelli17@gmail.com
A30: ALBERGHI | B30: GHIGHETTA | C30: via Borgo Mazzini 40 | D30: APECCHIO | G30: doradimaggio@libero.it
A31: ALLOGGI AGRITURISTICI | B31: AGRITURISMO LA ROCCA | D31: APECCHIO | E31: località la rocca | G31: a.parlani@alice.it
A32: ALLOGGI AGRITURISTICI | B32: AGRITURISMO CA' PIERPAOLI | D32: APECCHIO | E32: località Ca' Pierpaoli | F32: www.chipierpaoli.it | G32: info@chipierpaoli.it
A33: ALLOGGI AGRITURISTICI | B33: AGRITURISMO PIANDIMOLINO | C33: località Pian di Molino 16 | D33: APECCHIO | E33: PIAN DI MOLINO | F33: www.agriturismopiandimolino.it | G33: info@agriturismopiandimolino.it
A34: BED & BREAKFAST | B34: B&B GRANCI MARIA GRAZIA | C34: via Martiri della Liberta' 20 | D34: APECCHIO | E34: APECCHIO
A35: TURISMO RURALE | B35: LE CIOCCHE | D35: APECCHIO | E35: APECCHIO | G35: ale_cipi@live.it
A36: ALLOGGI AGRITURISTICI | B36: FONTE SOMMA | D36: APECCHIO | E36: loc.Fontesomma | F36: www.fontesomma.it | G36: info@fontesomma.it
A37: TURISMO RURALE | B37: COL ALPI | C37: via Circonvallazione 40 | D37: APECCHIO | E37: APECCHIO | G37: ilaesimo@virgilio.it
A38: TURISMO RURALE | B38: COUNTRY HOUSE CACCIABOCCA | C38: vocabolo Caselle 100 | D38: APECCHIO | E38: APECCHIO | F38: www.countryhousechiciabocca.it | G38: info@countryhousechiciabocca.it
A39: BED & BREAKFAST | B39: B&B MOCHI EDMONDO ADOLFO FEDERICO | C39: via dante alighieri 41 | D39: APECCHIO | E39: APECCHIO | G39: elenamochi@hotmail.it
A40: AREE DI SOSTA (PLEIN AIR) | B40: AREA DI SOSTA CAMPER | D40: APECCHIO | E40: APECCHIO
A41: ALLOGGI IN AFFITTO | B41: AFFITTACAMERE APPENNINO | C41: via Garibaldi 9 | D41: APECCHIO | G41: marcellamartinelli17@gmail.com
A42: ALLOGGI AGRITURISTICI | B42: AGRITURISMO PIEVE DI SAN PAOLO | C42: San Paolo di Fagnille 29 | D42: APECCHIO | E42: San Paolo di Fagnille | F42: www.pievesp.it | G42: info@pievesp.it
A43: ALLOGGI IN AFFITTO | B43: CASA DELLE ROSE | D43: APECCHIO | E43: APECCHIO | F43: www.valguerriera.it | G43: info@valguerriera.it
A44: ALLOGGI IN AFFITTO | B44: VECCHIA FORNACE | C44: vocabolo chignucci 1 | D44: APECCHIO | E44: APECCHIO | F44: www.valguerriera.it | G44: info@valguerriera.it
A45: ALLOGGI IN AFFITTO | B45: ESSICCATOIO | C45: vocabolo val d' acqua 1 | D45: APECCHIO | E45: APECCHIO | F45: www.valguerriera.it | G45: info@valguerriera.it
A46: TURISMO RURALE | B46: COUNTRY HOUSE LA SPINA | C46: vocabolo spina 1 | D46: APECCHIO | E46: APECCHIO | F46: www.countryhouselaspina.it | G46: info@countryhouselaspina.it
A47: ALLOGGI AGRITURISTICI | B47: CA' QUATTROCCHI | C47: via Roma 1 | D47: APECCHIO | E47: APECCHIO
A48: TURISMO RURALE | B48: LUCARAIA | C48: localita' Lucaraia 1 | D48: APECCHIO | E48: APECCHIO | G48: lpraziendaagricola@gmail.com
A49: ALBERGHI | B49: MONTENERONE | C49: localita' Pian di Trebbio 81 | D49: APECCHIO | E49: APECCHIO | F49: www.hotelmontenerone.it | G49: info@hotelmontenerone.it
A50: TURISMO RURALE | B50: COL DI FIORE | C50: loc Col di Fiore snc | D50: APECCHIO | E50: APECCHIO | G50: lpraziendaagricola@gmail.com
A51: ALLOGGI AGRITURISTICI | B51: CASELLINA | C51: loc. la Casellina 1 | D51: APECCHIO | E51: APECCHIO | G51: lpraziendaagricola@gmail.com
A52: ALLOGGI AGRITURISTICI | B52: TAVERNA | C52: vocabolo caselle 1 | D52: APECCHIO | E52: APECCHIO | G52: marialaura@jumpi.it;
A53: ALLOGGI AGRITURISTICI | B53: CHIGNONI | C53: vocabolo Chignoni 1 | D53: APECCHIO | E53: APECCHIO | F53: www.chignoni.it | G53: info@chignoni.it
A54: ALLOGGI AGRITURISTICI | B54: CA' CIRIGIOLO | C54: Loc. Casa Nuova di Cirigiolo s/n | D54: APECCHIO | E54: Apecchio | F54: www.cacirigiolo.it | G54: info@cacirigiolo.it
A55: ALLOGGI AGRITURISTICI | B55: VAL DEL LAGO | C55: vocabolo Acquapartita 1 | D55: APECCHIO | E55: loc. Val del Lago | G55: lpraziendaagricola@gmail.com
A56: ALLOGGI AGRITURISTICI | B56: CASELLE | D56: APECCHIO | E56: Apecchio | G56: marialaura@jumpi.it
A57: OSTELLI PER LA GIOVENTU' | B57: OSTELLO DELLA GIOVENTU' LA CHIUSURA (CUCCHIARINI ALDO LORIS) | C57: via dante alighieri 1 | D57: APECCHIO | E57: APECCHIO | G57: cooplamacina@info-net.it
A58: CASE PER FERIE | B58: VILLA SANTA MARIA | C58: via Cagli 89 | D58: APECCHIO | E58: fraz. Serravalle
A59: BED & BREAKFAST | B59: B&B IL BORGO | C59: BORGO MAZZINI 28 | D59: APECCHIO | E59: APECCHIO | G59: stevemugs@gmail.com
A60: ALLOGGI IN AFFITTO | B60: IL POGGIO DI D'ANGELI LIDIA AFFITTACAMERE | C60: Via Poggio San Giovanni 17 | D60: AUDITORE | E60: AUDITORE | G60: info@baita7nani.com
A61: ALLOGGI IN AFFITTO | B61: IL POGGIO DI D'ANGELI LIDIA | C61: Via Poggio San Giovanni 9 | D61: AUDITORE | E61: AUDITORE | G61: info@baita7nani.com
A62: BED & BREAKFAST | B62: B&B IL GIARDINO DELLE NOCI | C62: Località Molino Ca' Guerra 48 | D62: AUDITORE | E62: loc. Casinina | G62: ilariasanti89@libero.it
A63: ALBERGHI | B63: IL TORRIONE | C63: via circonvallazione 14 | D63: AUDITORE | E63: AUDITORE | F63: www.albergoiltorrione.it | G63: info@albergoiltorrione.it
A64: ALBERGHI | B64: ANTICA OSTERIA DA ORESTE | C64: via Risorgimento 4 | D64: AUDITORE | E64: frazione CASININA | F64: www.osteria-daoreste.it | G64: info@osteria-daoreste.it
A65: TURISMO RURALE | B65: COUNTRY HOUSE VILLA CISCA | C65: localita' molino fulvi 14 | D65: AUDITORE | E65: AUDITORE | F65: www.villacisca.com | G65: info@villacisca.com
A66: BED & BREAKFAST | B66: B&B TELE GIANNA | C66: via G. Leopardi 6 | D66: AUDITORE | E66: CASININA | F66: www.bb.telegianna.it | G66: carla2009@alice.it
A67: ALTRI ALLOGGI PRIVATI | B67: LA LUNA NELL'ORTO | C67: via Madonna Rafaneto 18 | D67: BARCHI | E67: loc.Rafaneto | F67: www.lalunanellorto.it | G67: petrabartels@libero.it
A68: ALLOGGI IN AFFITTO | B68: LA GIRAVOLTA | C68: via G. Campioli 10 | D68: BARCHI | F68: www.lagiravolta.eu | G68: info@lagiravolta.eu
A69: ALLOGGI IN AFFITTO | B69: VILLA RODI | C69: via Montesoffio 45 | D69: BARCHI | G69: d.falcinelli@cia.it
A70: ALTRI ALLOGGI PRIVATI | B70: VILLA AGAPANTUS | C70: via Villa di Monte Campagna 27 | D70: BARCHI | G70: francini_m@hotmail.com
A71: ALLOGGI AGRITURISTICI | B71: FONTE PAROLLA AGRITURISMO | C71: via Villa del Monte Campagna 13 | D71: BARCHI | E71: loc. Villa del Monte | F71: www.fonteparolla.it | G71: info@fonteparolla.it
A72: ALLOGGI AGRITURISTICI | B72: FORESTERIA AGRITURISTICA STRADA DEI CAMPIOLI | C72: via Giardino Campioli 31 | D72: BARCHI | F72: www.stradadeicampioli.it | G72: info@stradadeicampioli.it
A73: TURISMO RURALE | B73: COUNTRY HOUSE MONTESOFFIO | C73: localita' montesoffio 5 | D73: BARCHI | E73: BARCHI | F73: www.montesoffio.com | G73: info@montesoffio.com
A74: AREE DI SOSTA (PLEIN AIR) | B74: AREA DI SOSTA CAMPER | D74: BARCHI
A75: ALLOGGI AGRITURISTICI | B75: CAL FATTORE | C75: via Case Sparse snc | D75: BELFORTE ALL'ISAURO | G75: elebarbie@hotmail.it
A76: ALTRI ALLOGGI PRIVATI | B76: ROSSI ROSSANO | C76: via Angelini 4 | D76: BELFORTE ALL'ISAURO | G76: rossanorossi@hotmail.com
A77: ALTRI ALLOGGI PRIVATI | B77: CASALE FATTORIA GOSTOLI | C77: via Molino 16 | D77: BELFORTE ALL'ISAURO | G77: ilenia.battiato@tiscali.it
A78: ALBERGHI | B78: HOTEL LA RUPE | C78: via Meta 76 | D78: BORGO PACE | E78: BORGO PACE | G78: elisa@emtur.it
A79: BED & BREAKFAST | B79: B&B QUIETE SUL META | C79: via Papa Clemente XI 4 | D79: BORGO PACE | F79: www.quietesulmeta.com | G79: info@quietesulmeta.com
A80: BED & BREAKFAST | B80: B&B VALDERICARTE | C80: loc. Valderica 8 | D80: BORGO PACE | E80: LAMOLI | F80: www.valdericarte.com | G80: stella@valdericarte.com
A81: ALLOGGI AGRITURISTICI | B81: AGRITURISMO MORETTI MARCO | C81: localita' Campovecchio 1 | D81: BORGO PACE | E81: BORGO PACE
A82: ALBERGHI | B82: ALBERGO OASI SAN BENEDETTO | C82: via dell'Abbazia 7 | D82: BORGO PACE | E82: LAMOLI | G82: coloriappennino@libero.it
A83: ALLOGGI IN AFFITTO | B83: RANCO FABBRO | D83: BORGO PACE | E83: PARCHIULE | G83: prenotazioni@lamacina.it
A84: AREE DI SOSTA (PLEIN AIR) | B84: AREA DI SOSTA CAMPER | D84: BORGO PACE | E84: LOC. LAMOLI
A85: ALLOGGI AGRITURISTICI | B85: AGRITURISMO SANTI GILBERTO | C85: via Lame 18 | D85: BORGO PACE | E85: loc. Parchiule
A86: BED & BREAKFAST | B86: B&B AURO di BERNARDINI IVO | C86: loc. Molino 19 | D86: BORGO PACE | E86: BORGO PACE | G86: ivobernardini@libero.it
A87: ALLOGGI AGRITURISTICI | B87: AGRITURISMO ALPE DELLA LUNA | D87: BORGO PACE | E87: Vildonnino | F87: http://www.alpedellaluna.it/ | G87: agr@alpedellaluna.it
A88: ALBERGHI | B88: LA DILIGENZA | C88: piazza del Pino 9 | D88: BORGO PACE | E88: BORGO PACE | F88: www.anticalocandaladiligenza.it | G88: info@centrobebladiligenza.it
A89: RIFUGI | B89: OASI SAN BENEDETTO | C89: via dell' Abbazia 13 | D89: BORGO PACE | E89: BORGO PACE | G89: trabaria@libero.it
A90: OSTELLI PER LA GIOVENTU' | B90: OSTELLO PER LA GIOVENTU' | C90: via dell' Abbazia 40 | D90: BORGO PACE | E90: LAMOLI | G90: lamoli@oasisanbenedetto.it
A91: ALLOGGI AGRITURISTICI | B91: AGRITURISMO IL GINEPRO | C91: localita' Figgiano 46 | D91: BORGO PACE | E91: BORGO PACE | G91: info@ilgineprofigiano.com
A92: ALLOGGI AGRITURISTICI | B92: AGRITURISMO SACCHIA ART FARM | D92: BORGO PACE | E92: loc. Sacchia | F92: www.sacchiafarm.com | G92: info@sacchiafarm.com
A93: ALTRI ALLOGGI PRIVATI | B93: PAOLO CANGINI | C93: loc. Acquaviva 25 | D93: CAGLI
A94: ALTRI ALLOGGI PRIVATI | B94: PAVONI LUCIO | C94: via Don Minzoni, 66 66/a | D94: CAGLI | G94: lucia.pavoni.18@gmail.com
A95: ALTRI ALLOGGI PRIVATI | B95: GIUNTI FRANCESCO | C95: via Case Sparse 85 | D95: CAGLI | E95: loc. Naro
A96: BED & BREAKFAST | B96: B&B VILLA ADA | C96: via B.Buozzi 37 | D96: CAGLI | F96: http://villaadacagli.tumblr.com/ | G96: villaadacagli@gmail.com
A97: TURISMO RURALE | B97: COUNTRY HOUSE IL GIORDANO,SASSO DELLA ROCCA | C97: via Centro Pieia 16,45 | D97: CAGLI | E97: Centro Pieia 16; Centro Pieia 45 | F97: www.pieiavacanze.it | G97: info@pieiavacanze.it
A98: BED & BREAKFAST | B98: B&B LA VILLA DEGLI ORTI | C98: via Flaminia Nord 153 | D98: CAGLI | G98: m.tassi@libero.it
A99: ALLOGGI AGRITURISTICI | B99: L'ONCIA | D99: CAGLI | E99: loc. Ca' Serra | G99: zio.mele@libero.it
A100: TURISMO RURALE | B100: VILLA DEGLI ORTI | C100: via Flaminia Nord 153 | D100: CAGLI | G100: info@ortiamo.it
...

Sheet prezzi_raw
A1: Column1 | B1: xxx | C1: Column3
A2: xxx
C4: xxx
A5: CITTA' | C5: PREZZO MEDIO
A7: URBINO | C7: 31
A8: ACQUALAGNA | C8: 75
A9: APECCHIO | C9: 77
A10: AUDITORE | C10: 93
A11: BARCHI | C11: 83
A12: BELFORTE ALL'ISAURO | C12: 49
A13: BORGO PACE | C13: 58
A14: CAGLI | C14: 64
A15: CANTIANO | C15: 106
A16: CARPEGNA | C16: 118
A17: CARTOCETO | C17: 36
A18: FANO | C18: 120
... A243: TORRE SAN PATRIZIO | C243: 50

Sheet Strutture ricettive_lavorata
A1: Categoria | B1: Denominazione | C1: Indirizzo | D1: Città | E1: Localita | F1: Indirizzo internet | G1: Indirizzo di posta elettronica
A2: TURISMO RURALE | B2: Country House Localita' Girofalco | C2: Via Girfalco 26 | D2: URBINO | F2: www.girfalco.it | G2: info@girfalco.it
A3: ALTRI ALLOGGI PRIVATI | B3: Stagnozzi Stefania | C3: Via Candigliano 5 | D3: ACQUALAGNA | E3: ACQUALAGNA | G3: gigliovitto@libero.it
A4: ALTRI ALLOGGI PRIVATI | B4: Gorgolini Alessandro | C4: Via San Gregorio 9 | D4: ACQUALAGNA | E4: ACQUALAGNA | G4: ale.gorgolini@gmail.com
A5: ALBERGHI | B5: Leon D'Oro | C5: Via Flaminia 213 | D5: ACQUALAGNA | E5: ACQUALAGNA
A6: ALBERGHI | B6: Albergo Domus Mariae | C6: Viale Ezio Scaglioni 17 | D6: ACQUALAGNA | E6: ACQUALAGNA | G6: giulianaspini@gmail.com
A7: ALTRI ALLOGGI PRIVATI | B7: Torre Colombara Di Frontino | C7: Strada Frontino 24/B | D7: ACQUALAGNA | E7: ACQUALAGNA | G7: luccardi.sandro@gmail.com
A8: BED & BREAKFAST | B8: B&B Aquilegia | C8: Via Furlo 12 | D8: ACQUALAGNA | E8: FURLO | F8: www.aquilegiabeb.com | G8: info@aquilegiabeb.com
A9: ALLOGGI AGRITURISTICI | B9: Del Frontino | C9: Strada Frontino 23 | D9: ACQUALAGNA | E9: ACQUALAGNA
A10: ALBERGHI | B10: La Ginestra | C10: Via Furlo 17 | D10: ACQUALAGNA | E10: ACQUALAGNA | F10: www.ginestrafurlo.it | G10: info@ginestrafurlo.it
A11: ALBERGHI | B11: Birra Al Pozzo | C11: Via Pianacce 12 | D11: ACQUALAGNA | E11: ACQUALAGNA | F11: www.birraalpozzo.it | G11: info@birraalpozzo.it
A12: BED & BREAKFAST | B12: B&B Cristini Cristina | C12: Strada Frontino 23 | D12: ACQUALAGNA | E12: ACQUALAGNA | G12: cri.cristini@alice.it
A13: BED & BREAKFAST | B13: B&B Martelloni Cesare | C13: Via Pianacce 67 | D13: ACQUALAGNA | E13: ACQUALAGNA | F13: www.lalocandadellabbazia.it | G13: info@lalocandadellabbazia.it
A14: ALBERGHI | B14: Albergo Meuble' Shine | C14: Via Aldo Gamba 54 | D14: ACQUALAGNA | E14: ACQUALAGNA
A15: ALLOGGI AGRITURISTICI | B15: Agriturismo Castellago | C15: Strada Castellaro 18 | D15: ACQUALAGNA | E15: ACQUALAGNA | G15: castellago@virgilio.it
A16: ALBERGHI | B16: Albergo Antico Furlo | C16: Via Flaminia 66 | D16: ACQUALAGNA | E16: ACQUALAGNA | F16: www.anticofurlo.it | G16: info@anticofurlo.it
A17: TURISMO RURALE | B17: Ca' Garavano | C17: Strada Frontino 21 | D17: ACQUALAGNA | E17: ACQUALAGNA | F17: www.cagaravano.com | G17: urbini.alessandro@alice.it
A18: ALTRI ALLOGGI PRIVATI | B18: Il Conio Di Giovanni Federico | C18: Strada Pietralatra 1 | D18: ACQUALAGNA | E18: ACQUALAGNA
A19: ALLOGGI AGRITURISTICI | B19: Agriturismo I Conti | C19: Via Pieve Del Colle 11 B | D19: ACQUALAGNA | E19: PIEVE DEL COLLE | F19: www.agriturismoiconti.it | G19: info@agriturismoiconti.it
A20: ALLOGGI AGRITURISTICI | B20: La Colombara | C20: Strada Frontino 24 | D20: ACQUALAGNA
A21: ALTRI ALLOGGI PRIVATI | B21: Stroppa Giuseppe | C21: Strada San Gregorio 12 | D21: ACQUALAGNA | E21: ACQUALAGNA | F21: http://lapanoramicadastroppa.webstarts.com/ | G21: stroppag@libero.it
A22: ALTRI ALLOGGI PRIVATI | B22: Serafini Giorgia | D22: ACQUALAGNA
A23: ALTRI ALLOGGI PRIVATI | B23: Betti Vincenzo | C23: Via Pole 69 | D23: ACQUALAGNA
A24: ALLOGGI IN AFFITTO | B24: Marcheholiday - Casale Degli Ulivi | C24: Strada San Gregorio 1 | D24: ACQUALAGNA | E24: LOCALITÀ CA DONNINO | F24: www.marcheholiday.it/ulivi | G24: info@marcheholiday.it
A25: AREE DI SOSTA (PLEIN AIR) | B25: Area Sosta Camper Parco Le Querce | C25: Via Pianacce 1 | D25: ACQUALAGNA | E25: FURLO | F25: parcodelfurlo.it | G25: info@parcodelfurlo.it
A26: ALTRI ALLOGGI PRIVATI | B26: Bacchiocchi Maria Elisa | C26: Via San Gregorio 17 | D26: ACQUALAGNA | G26: remigio.battistelli@gmail.com
A27: ALTRI ALLOGGI PRIVATI | B27: Marchetti Lorenza | C27: Via Fossato 37/B | D27: ACQUALAGNA | G27: thomas.clementi@hotmail.it
A28: BED & BREAKFAST | B28: B&B Biscubio | C28: Via Circonvallazione 46 | D28: APECCHIO | G28: marcellamartinelli17@gmail.com
A29: ALBERGHI | B29: Ghighetta | C29: Via Borgo Mazzini 40 | D29: APECCHIO | G29: doradimaggio@libero.it
A30: ALLOGGI AGRITURISTICI | B30: Agriturismo La Rocca | D30: APECCHIO | E30: LOCALITÀ LA ROCCA | G30: a.parlani@alice.it
A31: ALLOGGI AGRITURISTICI | B31: Agriturismo Ca' Pierpaoli | D31: APECCHIO | E31: LOCALITÀ CA PIERPAOLI | F31: www.chipierpaoli.it | G31: info@chipierpaoli.it
A32: ALLOGGI AGRITURISTICI | B32: Agriturismo Piandimolino | C32: Pian Di Molino 16 | D32: APECCHIO | E32: PIAN DI MOLINO | F32: www.agriturismopiandimolino.it | G32: info@agriturismopiandimolino.it
A33: BED & BREAKFAST | B33: B&B Granci Maria Grazia | C33: Via Martiri Della Liberta' 20 | D33: APECCHIO | E33: APECCHIO
A34: TURISMO RURALE | B34: Le Ciocche | D34: APECCHIO | E34: APECCHIO | G34: ale_cipi@live.it
A35: ALLOGGI AGRITURISTICI | B35: Fonte Somma | D35: APECCHIO | E35: LOCALITÀ FONTESOMMA | F35: www.fontesomma.it | G35: info@fontesomma.it
A36: TURISMO RURALE | B36: Col Alpi | C36: Via Circonvallazione 40 | D36: APECCHIO | E36: APECCHIO | G36: ilaesimo@virgilio.it
A37: TURISMO RURALE | B37: Country House Cacciabocca | C37: Vocabolo Caselle 100 | D37: APECCHIO | E37: APECCHIO | F37: www.countryhousechiciabocca.it | G37: info@countryhousechiciabocca.it
A38: BED & BREAKFAST | B38: B&B Mochi Edmondo Adolfo Federico | C38: Via Dante Alighieri 41 | D38: APECCHIO | E38: APECCHIO | G38: elenamochi@hotmail.it
A39: AREE DI SOSTA (PLEIN AIR) | B39: Area Di Sosta Camper | D39: APECCHIO | E39: APECCHIO
A40: ALLOGGI IN AFFITTO | B40: Affittacamere Appennino | C40: Via Garibaldi 9 | D40: APECCHIO | G40: marcellamartinelli17@gmail.com
A41: ALLOGGI AGRITURISTICI | B41: Agriturismo Pieve Di San Paolo | C41: San Paolo Di Fagnille 29 | D41: APECCHIO | E41: SAN PAOLO DI FAGNILLE | F41: www.pievesp.it | G41: info@pievesp.it
A42: ALLOGGI IN AFFITTO | B42: Casa Delle Rose | D42: APECCHIO | E42: APECCHIO | F42: www.valguerriera.it | G42: info@valguerriera.it
A43: ALLOGGI IN AFFITTO | B43: Vecchia Fornace | C43: Vocabolo Chignucci 1 | D43: APECCHIO | E43: APECCHIO | F43: www.valguerriera.it | G43: info@valguerriera.it
A44: ALLOGGI IN AFFITTO | B44: Essiccatoio | C44: Vocabolo Val D' Acqua 1 | D44: APECCHIO | E44: APECCHIO | F44: www.valguerriera.it | G44: info@valguerriera.it
A45: TURISMO RURALE | B45: Country House La Spina | C45: Vocabolo Spina 1 | D45: APECCHIO | E45: APECCHIO | F45: www.countryhouselaspina.it | G45: info@countryhouselaspina.it
A46: ALLOGGI AGRITURISTICI | B46: Ca' Quattrocchi | C46: Via Roma 1 | D46: APECCHIO | E46: APECCHIO
A47: TURISMO RURALE | B47: Lucaraia | C47: Lucaraia 1 | D47: APECCHIO | E47: APECCHIO | G47: lpraziendaagricola@gmail.com
A48: ALBERGHI | B48: Montenerone | C48: Pian Di Trebbio 81 | D48: APECCHIO | E48: APECCHIO | F48: www.hotelmontenerone.it | G48: info@hotelmontenerone.it
A49: TURISMO RURALE | B49: Col Di Fiore | C49: Col Di Fiore Snc | D49: APECCHIO | E49: APECCHIO | G49: lpraziendaagricola@gmail.com
A50: ALLOGGI AGRITURISTICI | B50: Casellina | C50: La Casellina 1 | D50: APECCHIO | E50: APECCHIO | G50: lpraziendaagricola@gmail.com
A51: ALLOGGI AGRITURISTICI | B51: Taverna | C51: Vocabolo Caselle 1 | D51: APECCHIO | E51: APECCHIO | G51: marialaura@jumpi.it;
A52: ALLOGGI AGRITURISTICI | B52: Chignoni | C52: Vocabolo Chignoni 1 | D52: APECCHIO | E52: APECCHIO | F52: www.chignoni.it | G52: info@chignoni.it
A53: ALLOGGI AGRITURISTICI | B53: Ca' Cirigiolo | C53: Casa Nuova Di Cirigiolo S/N | D53: APECCHIO | E53: APECCHIO | F53: www.cacirigiolo.it | G53: info@cacirigiolo.it
A54: ALLOGGI AGRITURISTICI | B54: Val Del Lago | C54: Vocabolo Acquapartita 1 | D54: APECCHIO | E54: LOCALITÀ VAL DEL LAGO | G54: lpraziendaagricola@gmail.com
A55: ALLOGGI AGRITURISTICI | B55: Caselle | D55: APECCHIO | E55: APECCHIO | G55: marialaura@jumpi.it
A56: OSTELLI PER LA GIOVENTU' | B56: Ostello Della Gioventu' La Chiusura (Cucchiarini Aldo Loris) | C56: Via Dante Alighieri 1 | D56: APECCHIO | E56: APECCHIO | G56: cooplamacina@info-net.it
A57: CASE PER FERIE | B57: Villa Santa Maria | C57: Via Cagli 89 | D57: APECCHIO | E57: FRAZIONE SERRAVALLE
A58: BED & BREAKFAST | B58: B&B Il Borgo | C58: Borgo Mazzini 28 | D58: APECCHIO | E58: APECCHIO | G58: stevemugs@gmail.com
A59: ALLOGGI IN AFFITTO | B59: Il Poggio Di D'Angeli Lidia Affittacamere | C59: Via Poggio San Giovanni 17 | D59: AUDITORE | E59: AUDITORE | G59: info@baita7nani.com
A60: ALLOGGI IN AFFITTO | B60: Il Poggio Di D'Angeli Lidia | C60: Via Poggio San Giovanni 9 | D60: AUDITORE | E60: AUDITORE | G60: info@baita7nani.com
A61: BED & BREAKFAST | B61: B&B Il Giardino Delle Noci | C61: Molino Ca' Guerra 48 | D61: AUDITORE | E61: LOCALITÀ CASININA | G61: ilariasanti89@libero.it
A62: ALBERGHI | B62: Il Torrione | C62: Via Circonvallazione 14 | D62: AUDITORE | E62: AUDITORE | F62: www.albergoiltorrione.it | G62: info@albergoiltorrione.it
A63: ALBERGHI | B63: Antica Osteria Da Oreste | C63: Via Risorgimento 4 | D63: AUDITORE | E63: FRAZIONE CASININA | F63: www.osteria-daoreste.it | G63: info@osteria-daoreste.it
A64: TURISMO RURALE | B64: Country House Villa Cisca | C64: Molino Fulvi 14 | D64: AUDITORE | E64: AUDITORE | F64: www.villacisca.com | G64: info@villacisca.com
A65: BED & BREAKFAST | B65: B&B Tele Gianna | C65: Via G. Leopardi 6 | D65: AUDITORE | E65: CASININA | F65: www.bb.telegianna.it | G65: carla2009@alice.it
A66: ALTRI ALLOGGI PRIVATI | B66: La Luna Nell'Orto | C66: Via Madonna Rafaneto 18 | D66: BARCHI | E66: LOCALITÀ RAFANETO | F66: www.lalunanellorto.it | G66: petrabartels@libero.it
A67: ALLOGGI IN AFFITTO | B67: La Giravolta | C67: Via G. Campioli 10 | D67: BARCHI | F67: www.lagiravolta.eu | G67: info@lagiravolta.eu
A68: ALLOGGI IN AFFITTO | B68: Villa Rodi | C68: Via Montesoffio 45 | D68: BARCHI | G68: d.falcinelli@cia.it
A69: ALTRI ALLOGGI PRIVATI | B69: Villa Agapantus | C69: Via Villa Di Monte Campagna 27 | D69: BARCHI | G69: francini_m@hotmail.com
A70: ALLOGGI AGRITURISTICI | B70: Fonte Parolla Agriturismo | C70: Via Villa Del Monte Campagna 13 | D70: BARCHI | E70: LOCALITÀ VILLA DEL MONTE | F70: www.fonteparolla.it | G70: info@fonteparolla.it
A71: ALLOGGI AGRITURISTICI | B71: Foresteria Agrituristica Strada Dei Campioli | C71: Via Giardino Campioli 31 | D71: BARCHI | F71: www.stradadeicampioli.it | G71: info@stradadeicampioli.it
A72: TURISMO RURALE | B72: Country House Montesoffio | C72: Montesoffio 5 | D72: BARCHI | E72: BARCHI | F72: www.montesoffio.com | G72: info@montesoffio.com
A73: AREE DI SOSTA (PLEIN AIR) | B73: Area Di Sosta Camper | D73: BARCHI
A74: ALLOGGI AGRITURISTICI | B74: Cal Fattore | C74: Via Case Sparse Snc | D74: BELFORTE ALL'ISAURO | G74: elebarbie@hotmail.it
A75: ALTRI ALLOGGI PRIVATI | B75: Rossi Rossano | C75: Via Angelini 4 | D75: BELFORTE ALL'ISAURO | G75: rossanorossi@hotmail.com
A76: ALTRI ALLOGGI PRIVATI | B76: Casale Fattoria Gostoli | C76: Via Molino 16 | D76: BELFORTE ALL'ISAURO | G76: ilenia.battiato@tiscali.it
A77: ALBERGHI | B77: Hotel La Rupe | C77: Via Meta 76 | D77: BORGO PACE | E77: BORGO PACE | G77: elisa@emtur.it
A78: BED & BREAKFAST | B78: B&B Quiete Sul Meta | C78: Via Papa Clemente Xi 4 | D78: BORGO PACE | F78: www.quietesulmeta.com | G78: info@quietesulmeta.com
A79: BED & BREAKFAST | B79: B&B Valdericarte | C79: Valderica 8 | D79: BORGO PACE | E79: LAMOLI | F79: www.valdericarte.com | G79: stella@valdericarte.com
A80: ALLOGGI AGRITURISTICI | B80: Agriturismo Moretti Marco | C80: Campovecchio 1 | D80: BORGO PACE | E80: BORGO PACE
A81: ALBERGHI | B81: Albergo Oasi San Benedetto | C81: Via Dell'Abbazia 7 | D81: BORGO PACE | E81: LAMOLI | G81: coloriappennino@libero.it
A82: ALLOGGI IN AFFITTO | B82: Ranco Fabbro | D82: BORGO PACE | E82: PARCHIULE | G82: prenotazioni@lamacina.it
A83: AREE DI SOSTA (PLEIN AIR) | B83: Area Di Sosta Camper | D83: BORGO PACE | E83: LOCALITÀ LAMOLI
A84: ALLOGGI AGRITURISTICI | B84: Agriturismo Santi Gilberto | C84: Via Lame 18 | D84: BORGO PACE | E84: LOCALITÀ PARCHIULE
A85: BED & BREAKFAST | B85: B&B Auro Di Bernardini Ivo | C85: Molino 19 | D85: BORGO PACE | E85: BORGO PACE | G85: ivobernardini@libero.it
A86: ALLOGGI AGRITURISTICI | B86: Agriturismo Alpe Della Luna | D86: BORGO PACE | E86: VILDONNINO | F86: http://www.alpedellaluna.it/ | G86: agr@alpedellaluna.it
A87: ALBERGHI | B87: La Diligenza | C87: Piazza Del Pino 9 | D87: BORGO PACE | E87: BORGO PACE | F87: www.anticalocandaladiligenza.it | G87: info@centrobebladiligenza.it
A88: RIFUGI | B88: Oasi San Benedetto | C88: Via Dell' Abbazia 13 | D88: BORGO PACE | E88: BORGO PACE | G88: trabaria@libero.it
A89: OSTELLI PER LA GIOVENTU' | B89: Ostello Per La Gioventu' | C89: Via Dell' Abbazia 40 | D89: BORGO PACE | E89: LAMOLI | G89: lamoli@oasisanbenedetto.it
A90: ALLOGGI AGRITURISTICI | B90: Agriturismo Il Ginepro | C90: Figgiano 46 | D90: BORGO PACE | E90: BORGO PACE | G90: info@ilgineprofigiano.com
A91: ALLOGGI AGRITURISTICI | B91: Agriturismo Sacchia Art Farm | D91: BORGO PACE | E91: LOCALITÀ SACCHIA | F91: www.sacchiafarm.com | G91: info@sacchiafarm.com
A92: ALTRI ALLOGGI PRIVATI | B92: Paolo Cangini | C92: Acquaviva 25 | D92: CAGLI
A93: ALTRI ALLOGGI PRIVATI | B93: Pavoni Lucio | C93: Via Don Minzoni 66 66/A | D93: CAGLI | G93: lucia.pavoni.18@gmail.com
A94: ALTRI ALLOGGI PRIVATI | B94: Giunti Francesco | C94: Via Case Sparse 85 | D94: CAGLI | E94: LOCALITÀ NARO
A95: BED & BREAKFAST | B95: B&B Villa Ada | C95: Via B.Buozzi 37 | D95: CAGLI | F95: http://villaadacagli.tumblr.com/ | G95: villaadacagli@gmail.com
A96: TURISMO RURALE | B96: Country House Il Giordano,Sasso Della Rocca | C96: Via Centro Pieia 1645 | D96: CAGLI | F96: www.pieiavacanze.it | G96: info@pieiavacanze.it
A97: BED & BREAKFAST | B97: B&B La Villa Degli Orti | C97: Via Flaminia Nord 153 | D97: CAGLI | G97: m.tassi@libero.it
A98: ALLOGGI AGRITURISTICI | B98: L'Oncia | D98: CAGLI | E98: LOCALITÀ CA SERRA | G98: zio.mele@libero.it
A99: TURISMO RURALE | B99: Villa Degli Orti | C99: Via Flaminia Nord 153 | D99: CAGLI | G99: info@ortiamo.it
A100: ALLOGGI IN AFFITTO | B100: La Piazza | C100: Piazza Matteotti 6 | D100: CAGLI | F100: www.casavacanzelapiazza.it | G100: info@casavacanzelapiazza.it
...

Sheet prezzi_lavorata
A1: CITTA' | B1: PREZZO MEDIO
A2: URBINO | B2: 31
A3: ACQUALAGNA | B3: 75
A4: APECCHIO | B4: 77
A5: AUDITORE | B5: 93
A6: BARCHI | B6: 83
A7: BELFORTE ALL'ISAURO | B7: 49
A8: BORGO PACE | B8: 58
A9: CAGLI | B9: 64
A10: CANTIANO | B10: 106
A11: CARPEGNA | B11: 118
A12: CARTOCETO | B12: 36
A13: FANO | B13: 120
... A235: TORRE SAN PATRIZIO | B235: 50

Sheet MergePrezzoMedio
A1: Categoria | B1: Denominazione | C1: Indirizzo | D1: Città | E1: PREZZO MEDIO | F1: Localita | G1: Indirizzo internet | H1: Indirizzo di posta elettronica
A2: TURISMO RURALE | B2: Country House Localita' Girofalco | C2: Via Girfalco 26 | D2: URBINO | E2: 31 | G2: www.girfalco.it | H2: info@girfalco.it
A3: ALTRI ALLOGGI PRIVATI | B3: Stagnozzi Stefania | C3: Via Candigliano 5 | D3: ACQUALAGNA | E3: 75 | F3: ACQUALAGNA | H3: gigliovitto@libero.it
A4: ALTRI ALLOGGI PRIVATI | B4: Gorgolini Alessandro | C4: Via San Gregorio 9 | D4: ACQUALAGNA | E4: 75 | F4: ACQUALAGNA | H4: ale.gorgolini@gmail.com
A5: ALBERGHI | B5: Leon D'Oro | C5: Via Flaminia 213 | D5: ACQUALAGNA | E5: 75 | F5: ACQUALAGNA
A6: ALBERGHI | B6: Albergo Domus Mariae | C6: Viale Ezio Scaglioni 17 | D6: ACQUALAGNA | E6: 75 | F6: ACQUALAGNA | H6: giulianaspini@gmail.com
A7: ALTRI ALLOGGI PRIVATI | B7: Torre Colombara Di Frontino | C7: Strada Frontino 24/B | D7: ACQUALAGNA | E7: 75 | F7: ACQUALAGNA | H7: luccardi.sandro@gmail.com
A8: BED & BREAKFAST | B8: B&B Aquilegia | C8: Via Furlo 12 | D8: ACQUALAGNA | E8: 75 | F8: FURLO | G8: www.aquilegiabeb.com | H8: info@aquilegiabeb.com
A9: ALLOGGI AGRITURISTICI | B9: Del Frontino | C9: Strada Frontino 23 | D9: ACQUALAGNA | E9: 75 | F9: ACQUALAGNA
A10: ALBERGHI | B10: La Ginestra | C10: Via Furlo 17 | D10: ACQUALAGNA | E10: 75 | F10: ACQUALAGNA | G10: www.ginestrafurlo.it | H10: info@ginestrafurlo.it
A11: ALBERGHI | B11: Birra Al Pozzo | C11: Via Pianacce 12 | D11: ACQUALAGNA | E11: 75 | F11: ACQUALAGNA | G11: www.birraalpozzo.it | H11: info@birraalpozzo.it
A12: BED & BREAKFAST | B12: B&B Cristini Cristina | C12: Strada Frontino 23 | D12: ACQUALAGNA | E12: 75 | F12: ACQUALAGNA | H12: cri.cristini@alice.it
A13: BED & BREAKFAST | B13: B&B Martelloni Cesare | C13: Via Pianacce 67 | D13: ACQUALAGNA | E13: 75 | F13: ACQUALAGNA | G13: www.lalocandadellabbazia.it | H13: info@lalocandadellabbazia.it
A14: ALBERGHI | B14: Albergo Meuble' Shine | C14: Via Aldo Gamba 54 | D14: ACQUALAGNA | E14: 75 | F14: ACQUALAGNA
A15: ALLOGGI AGRITURISTICI | B15: Agriturismo Castellago | C15: Strada Castellaro 18 | D15: ACQUALAGNA | E15: 75 | F15: ACQUALAGNA | H15: castellago@virgilio.it
A16: ALBERGHI | B16: Albergo Antico Furlo | C16: Via Flaminia 66 | D16: ACQUALAGNA | E16: 75 | F16: ACQUALAGNA | G16: www.anticofurlo.it | H16: info@anticofurlo.it
A17: TURISMO RURALE | B17: Ca' Garavano | C17: Strada Frontino 21 | D17: ACQUALAGNA | E17: 75 | F17: ACQUALAGNA | G17: www.cagaravano.com | H17: urbini.alessandro@alice.it
A18: ALTRI ALLOGGI PRIVATI | B18: Il Conio Di Giovanni Federico | C18: Strada Pietralatra 1 | D18: ACQUALAGNA | E18: 75 | F18: ACQUALAGNA
A19: ALLOGGI AGRITURISTICI | B19: Agriturismo I Conti | C19: Via Pieve Del Colle 11 B | D19: ACQUALAGNA | E19: 75 | F19: PIEVE DEL COLLE | G19: www.agriturismoiconti.it | H19: info@agriturismoiconti.it
A20: ALLOGGI AGRITURISTICI | B20: La Colombara | C20: Strada Frontino 24 | D20: ACQUALAGNA | E20: 75
A21: ALTRI ALLOGGI PRIVATI | B21: Stroppa Giuseppe | C21: Strada San Gregorio 12 | D21: ACQUALAGNA | E21: 75 | F21: ACQUALAGNA | G21: http://lapanoramicadastroppa.webstarts.com/ | H21: stroppag@libero.it
A22: ALTRI ALLOGGI PRIVATI | B22: Serafini Giorgia | D22: ACQUALAGNA | E22: 75
A23: ALTRI ALLOGGI PRIVATI | B23: Betti Vincenzo | C23: Via Pole 69 | D23: ACQUALAGNA | E23: 75
A24: ALLOGGI IN AFFITTO | B24: Marcheholiday - Casale Degli Ulivi | C24: Strada San Gregorio 1 | D24: ACQUALAGNA | E24: 75 | F24: LOCALITÀ CA DONNINO | G24: www.marcheholiday.it/ulivi | H24: info@marcheholiday.it
A25: AREE DI SOSTA (PLEIN AIR) | B25: Area Sosta Camper Parco Le Querce | C25: Via Pianacce 1 | D25: ACQUALAGNA | E25: 75 | F25: FURLO | G25: parcodelfurlo.it | H25: info@parcodelfurlo.it
A26: ALTRI ALLOGGI PRIVATI | B26: Bacchiocchi Maria Elisa | C26: Via San Gregorio 17 | D26: ACQUALAGNA | E26: 75 | H26: remigio.battistelli@gmail.com
A27: ALTRI ALLOGGI PRIVATI | B27: Marchetti Lorenza | C27: Via Fossato 37/B | D27: ACQUALAGNA | E27: 75 | H27: thomas.clementi@hotmail.it
A28: BED & BREAKFAST | B28: B&B Biscubio | C28: Via Circonvallazione 46 | D28: APECCHIO | E28: 77 | H28: marcellamartinelli17@gmail.com
A29: ALBERGHI | B29: Ghighetta | C29: Via Borgo Mazzini 40 | D29: APECCHIO | E29: 77 | H29: doradimaggio@libero.it
A30: ALLOGGI AGRITURISTICI | B30: Agriturismo La Rocca | D30: APECCHIO | E30: 77 | F30: LOCALITÀ LA ROCCA | H30: a.parlani@alice.it
A31: ALLOGGI AGRITURISTICI | B31: Agriturismo Ca' Pierpaoli | D31: APECCHIO | E31: 77 | F31: LOCALITÀ CA PIERPAOLI | G31: www.chipierpaoli.it | H31: info@chipierpaoli.it
A32: ALLOGGI AGRITURISTICI | B32: Agriturismo Piandimolino | C32: Pian Di Molino 16 | D32: APECCHIO | E32: 77 | F32: PIAN DI MOLINO | G32: www.agriturismopiandimolino.it | H32: info@agriturismopiandimolino.it
A33: BED & BREAKFAST | B33: B&B Granci Maria Grazia | C33: Via Martiri Della Liberta' 20 | D33: APECCHIO | E33: 77 | F33: APECCHIO
A34: TURISMO RURALE | B34: Le Ciocche | D34: APECCHIO | E34: 77 | F34: APECCHIO | H34: ale_cipi@live.it
A35: ALLOGGI AGRITURISTICI | B35: Fonte Somma | D35: APECCHIO | E35: 77 | F35: LOCALITÀ FONTESOMMA | G35: www.fontesomma.it | H35: info@fontesomma.it
A36: TURISMO RURALE | B36: Col Alpi | C36: Via Circonvallazione 40 | D36: APECCHIO | E36: 77 | F36: APECCHIO | H36: ilaesimo@virgilio.it
A37: TURISMO RURALE | B37: Country House Cacciabocca | C37: Vocabolo Caselle 100 | D37: APECCHIO | E37: 77 | F37: APECCHIO | G37: www.countryhousechiciabocca.it | H37: info@countryhousechiciabocca.it
A38: BED & BREAKFAST | B38: B&B Mochi Edmondo Adolfo Federico | C38: Via Dante Alighieri 41 | D38: APECCHIO | E38: 77 | F38: APECCHIO | H38: elenamochi@hotmail.it
A39: AREE DI SOSTA (PLEIN AIR) | B39: Area Di Sosta Camper | D39: APECCHIO | E39: 77 | F39: APECCHIO
A40: ALLOGGI IN AFFITTO | B40: Affittacamere Appennino | C40: Via Garibaldi 9 | D40: APECCHIO | E40: 77 | H40: marcellamartinelli17@gmail.com
A41: ALLOGGI AGRITURISTICI | B41: Agriturismo Pieve Di San Paolo | C41: San Paolo Di Fagnille 29 | D41: APECCHIO | E41: 77 | F41: SAN PAOLO DI FAGNILLE | G41: www.pievesp.it | H41: info@pievesp.it
A42: ALLOGGI IN AFFITTO | B42: Casa Delle Rose | D42: APECCHIO | E42: 77 | F42: APECCHIO | G42: www.valguerriera.it | H42: info@valguerriera.it
A43: ALLOGGI IN AFFITTO | B43: Vecchia Fornace | C43: Vocabolo Chignucci 1 | D43: APECCHIO | E43: 77 | F43: APECCHIO | G43: www.valguerriera.it | H43: info@valguerriera.it
A44: ALLOGGI IN AFFITTO | B44: Essiccatoio | C44: Vocabolo Val D' Acqua 1 | D44: APECCHIO | E44: 77 | F44: APECCHIO | G44: www.valguerriera.it | H44: info@valguerriera.it
A45: TURISMO RURALE | B45: Country House La Spina | C45: Vocabolo Spina 1 | D45: APECCHIO | E45: 77 | F45: APECCHIO | G45: www.countryhouselaspina.it | H45: info@countryhouselaspina.it
A46: ALLOGGI AGRITURISTICI | B46: Ca' Quattrocchi | C46: Via Roma 1 | D46: APECCHIO | E46: 77 | F46: APECCHIO
A47: TURISMO RURALE | B47: Lucaraia | C47: Lucaraia 1 | D47: APECCHIO | E47: 77 | F47: APECCHIO | H47: lpraziendaagricola@gmail.com
A48: ALBERGHI | B48: Montenerone | C48: Pian Di Trebbio 81 | D48: APECCHIO | E48: 77 | F48: APECCHIO | G48: www.hotelmontenerone.it | H48: info@hotelmontenerone.it
A49: TURISMO RURALE | B49: Col Di Fiore | C49: Col Di Fiore Snc | D49: APECCHIO | E49: 77 | F49: APECCHIO | H49: lpraziendaagricola@gmail.com
A50: ALLOGGI AGRITURISTICI | B50: Casellina | C50: La Casellina 1 | D50: APECCHIO | E50: 77 | F50: APECCHIO | H50: lpraziendaagricola@gmail.com
A51: ALLOGGI AGRITURISTICI | B51: Taverna | C51: Vocabolo Caselle 1 | D51: APECCHIO | E51: 77 | F51: APECCHIO | H51: marialaura@jumpi.it;
A52: ALLOGGI AGRITURISTICI | B52: Chignoni | C52: Vocabolo Chignoni 1 | D52: APECCHIO | E52: 77 | F52: APECCHIO | G52: www.chignoni.it | H52: info@chignoni.it
A53: ALLOGGI AGRITURISTICI | B53: Ca' Cirigiolo | C53: Casa Nuova Di Cirigiolo S/N | D53: APECCHIO | E53: 77 | F53: APECCHIO | G53: www.cacirigiolo.it | H53: info@cacirigiolo.it
A54: ALLOGGI AGRITURISTICI | B54: Val Del Lago | C54: Vocabolo Acquapartita 1 | D54: APECCHIO | E54: 77 | F54: LOCALITÀ VAL DEL LAGO | H54: lpraziendaagricola@gmail.com
A55: ALLOGGI AGRITURISTICI | B55: Caselle | D55: APECCHIO | E55: 77 | F55: APECCHIO | H55: marialaura@jumpi.it
A56: OSTELLI PER LA GIOVENTU' | B56: Ostello Della Gioventu' La Chiusura (Cucchiarini Aldo Loris) | C56: Via Dante Alighieri 1 | D56: APECCHIO | E56: 77 | F56: APECCHIO | H56: cooplamacina@info-net.it
A57: CASE PER FERIE | B57: Villa Santa Maria | C57: Via Cagli 89 | D57: APECCHIO | E57: 77 | F57: FRAZIONE SERRAVALLE
A58: BED & BREAKFAST | B58: B&B Il Borgo | C58: Borgo Mazzini 28 | D58: APECCHIO | E58: 77 | F58: APECCHIO | H58: stevemugs@gmail.com
A59: ALLOGGI IN AFFITTO | B59: Il Poggio Di D'Angeli Lidia Affittacamere | C59: Via Poggio San Giovanni 17 | D59: AUDITORE | E59: 93 | F59: AUDITORE | H59: info@baita7nani.com
A60: ALLOGGI IN AFFITTO | B60: Il Poggio Di D'Angeli Lidia | C60: Via Poggio San Giovanni 9 | D60: AUDITORE | E60: 93 | F60: AUDITORE | H60: info@baita7nani.com
A61: BED & BREAKFAST | B61: B&B Il Giardino Delle Noci | C61: Molino Ca' Guerra 48 | D61: AUDITORE | E61: 93 | F61: LOCALITÀ CASININA | H61: ilariasanti89@libero.it
A62: ALBERGHI | B62: Il Torrione | C62: Via Circonvallazione 14 | D62: AUDITORE | E62: 93 | F62: AUDITORE | G62: www.albergoiltorrione.it | H62: info@albergoiltorrione.it
A63: ALBERGHI | B63: Antica Osteria Da Oreste | C63: Via Risorgimento 4 | D63: AUDITORE | E63: 93 | F63: FRAZIONE CASININA | G63: www.osteria-daoreste.it | H63: info@osteria-daoreste.it
A64: TURISMO RURALE | B64: Country House Villa Cisca | C64: Molino Fulvi 14 | D64: AUDITORE | E64: 93 | F64: AUDITORE | G64: www.villacisca.com | H64: info@villacisca.com
A65: BED & BREAKFAST | B65: B&B Tele Gianna | C65: Via G. Leopardi 6 | D65: AUDITORE | E65: 93 | F65: CASININA | G65: www.bb.telegianna.it | H65: carla2009@alice.it
A66: ALTRI ALLOGGI PRIVATI | B66: La Luna Nell'Orto | C66: Via Madonna Rafaneto 18 | D66: BARCHI | E66: 83 | F66: LOCALITÀ RAFANETO | G66: www.lalunanellorto.it | H66: petrabartels@libero.it
A67: ALLOGGI IN AFFITTO | B67: La Giravolta | C67: Via G. Campioli 10 | D67: BARCHI | E67: 83 | G67: www.lagiravolta.eu | H67: info@lagiravolta.eu
A68: ALLOGGI IN AFFITTO | B68: Villa Rodi | C68: Via Montesoffio 45 | D68: BARCHI | E68: 83 | H68: d.falcinelli@cia.it
A69: ALTRI ALLOGGI PRIVATI | B69: Villa Agapantus | C69: Via Villa Di Monte Campagna 27 | D69: BARCHI | E69: 83 | H69: francini_m@hotmail.com
A70: ALLOGGI AGRITURISTICI | B70: Fonte Parolla Agriturismo | C70: Via Villa Del Monte Campagna 13 | D70: BARCHI | E70: 83 | F70: LOCALITÀ VILLA DEL MONTE | G70: www.fonteparolla.it | H70: info@fonteparolla.it
A71: ALLOGGI AGRITURISTICI | B71: Foresteria Agrituristica Strada Dei Campioli | C71: Via Giardino Campioli 31 | D71: BARCHI | E71: 83 | G71: www.stradadeicampioli.it | H71: info@stradadeicampioli.it
A72: TURISMO RURALE | B72: Country House Montesoffio | C72: Montesoffio 5 | D72: BARCHI | E72: 83 | F72: BARCHI | G72: www.montesoffio.com | H72: info@montesoffio.com
A73: AREE DI SOSTA (PLEIN AIR) | B73: Area Di Sosta Camper | D73: BARCHI | E73: 83
A74: ALLOGGI AGRITURISTICI | B74: Cal Fattore | C74: Via Case Sparse Snc | D74: BELFORTE ALL'ISAURO | E74: 49 | H74: elebarbie@hotmail.it
A75: ALTRI ALLOGGI PRIVATI | B75: Rossi Rossano | C75: Via Angelini 4 | D75: BELFORTE ALL'ISAURO | E75: 49 | H75: rossanorossi@hotmail.com
A76: ALTRI ALLOGGI PRIVATI | B76: Casale Fattoria Gostoli | C76: Via Molino 16 | D76: BELFORTE ALL'ISAURO | E76: 49 | H76: ilenia.battiato@tiscali.it
A77: ALBERGHI | B77: Hotel La Rupe | C77: Via Meta 76 | D77: BORGO PACE | E77: 58 | F77: BORGO PACE | H77: elisa@emtur.it
A78: BED & BREAKFAST | B78: B&B Quiete Sul Meta | C78: Via Papa Clemente Xi 4 | D78: BORGO PACE | E78: 58 | G78: www.quietesulmeta.com | H78: info@quietesulmeta.com
A79: BED & BREAKFAST | B79: B&B Valdericarte | C79: Valderica 8 | D79: BORGO PACE | E79: 58 | F79: LAMOLI | G79: www.valdericarte.com | H79: stella@valdericarte.com
A80: ALLOGGI AGRITURISTICI | B80: Agriturismo Moretti Marco | C80: Campovecchio 1 | D80: BORGO PACE | E80: 58 | F80: BORGO PACE
A81: ALBERGHI | B81: Albergo Oasi San Benedetto | C81: Via Dell'Abbazia 7 | D81: BORGO PACE | E81: 58 | F81: LAMOLI | H81: coloriappennino@libero.it
A82: ALLOGGI IN AFFITTO | B82: Ranco Fabbro | D82: BORGO PACE | E82: 58 | F82: PARCHIULE | H82: prenotazioni@lamacina.it
A83: AREE DI SOSTA (PLEIN AIR) | B83: Area Di Sosta Camper | D83: BORGO PACE | E83: 58 | F83: LOCALITÀ LAMOLI
A84: ALLOGGI AGRITURISTICI | B84: Agriturismo Santi Gilberto | C84: Via Lame 18 | D84: BORGO PACE | E84: 58 | F84: LOCALITÀ PARCHIULE
A85: BED & BREAKFAST | B85: B&B Auro Di Bernardini Ivo | C85: Molino 19 | D85: BORGO PACE | E85: 58 | F85: BORGO PACE | H85: ivobernardini@libero.it
A86: ALLOGGI AGRITURISTICI | B86: Agriturismo Alpe Della Luna | D86: BORGO PACE | E86: 58 | F86: VILDONNINO | G86: http://www.alpedellaluna.it/ | H86: agr@alpedellaluna.it
A87: ALBERGHI | B87: La Diligenza | C87: Piazza Del Pino 9 | D87: BORGO PACE | E87: 58 | F87: BORGO PACE | G87: www.anticalocandaladiligenza.it | H87: info@centrobebladiligenza.it
A88: RIFUGI | B88: Oasi San Benedetto | C88: Via Dell' Abbazia 13 | D88: BORGO PACE | E88: 58 | F88: BORGO PACE | H88: trabaria@libero.it
A89: OSTELLI PER LA GIOVENTU' | B89: Ostello Per La Gioventu' | C89: Via Dell' Abbazia 40 | D89: BORGO PACE | E89: 58 | F89: LAMOLI | H89: lamoli@oasisanbenedetto.it
A90: ALLOGGI AGRITURISTICI | B90: Agriturismo Il Ginepro | C90: Figgiano 46 | D90: BORGO PACE | E90: 58 | F90: BORGO PACE | H90: info@ilgineprofigiano.com
A91: ALLOGGI AGRITURISTICI | B91: Agriturismo Sacchia Art Farm | D91: BORGO PACE | E91: 58 | F91: LOCALITÀ SACCHIA | G91: www.sacchiafarm.com | H91: info@sacchiafarm.com
A92: ALTRI ALLOGGI PRIVATI | B92: Paolo Cangini | C92: Acquaviva 25 | D92: CAGLI | E92: 64
A93: ALTRI ALLOGGI PRIVATI | B93: Pavoni Lucio | C93: Via Don Minzoni 66 66/A | D93: CAGLI | E93: 64 | H93: lucia.pavoni.18@gmail.com
A94: ALTRI ALLOGGI PRIVATI | B94: Giunti Francesco | C94: Via Case Sparse 85 | D94: CAGLI | E94: 64 | F94: LOCALITÀ NARO
A95: BED & BREAKFAST | B95: B&B Villa Ada | C95: Via B.Buozzi 37 | D95: CAGLI | E95: 64 | G95: http://villaadacagli.tumblr.com/ | H95: villaadacagli@gmail.com
A96: TURISMO RURALE | B96: Country House Il Giordano,Sasso Della Rocca | C96: Via Centro Pieia 1645 | D96: CAGLI | E96: 64 | G96: www.pieiavacanze.it | H96: info@pieiavacanze.it
A97: BED & BREAKFAST | B97: B&B La Villa Degli Orti | C97: Via Flaminia Nord 153 | D97: CAGLI | E97: 64 | H97: m.tassi@libero.it
A98: ALLOGGI AGRITURISTICI | B98: L'Oncia | D98: CAGLI | E98: 64 | F98: LOCALITÀ CA SERRA | H98: zio.mele@libero.it
A99: TURISMO RURALE | B99: Villa Degli Orti | C99: Via Flaminia Nord 153 | D99: CAGLI | E99: 64 | H99: info@ortiamo.it
A100: ALLOGGI IN AFFITTO | B100: La Piazza | C100: Piazza Matteotti 6 | D100: CAGLI | E100: 64 | G100: www.casavacanzelapiazza.it | H100: info@casavacanzelapiazza.it
...

Sheet Raggruppa
A1: Città | B1: Categoria | C1: Qtà Strutture
A2: SENIGALLIA | B2: STABILIMENTI BALNEARI | C2: 130
A3: FANO | B3: ALTRI ALLOGGI PRIVATI | C3: 112
A4: SENIGALLIA | B4: ALTRI ALLOGGI PRIVATI | C4: 111
A5: ASCOLI PICENO | B5: BED & BREAKFAST | C5: 110
A6: SAN BENEDETTO DEL TRONTO | B6: STABILIMENTI BALNEARI | C6: 109
A7: GABICCE MARE | B7: ALBERGHI | C7: 82
A8: SENIGALLIA | B8: ALBERGHI | C8: 81
A9: CIVITANOVA MARCHE | B9: BED & BREAKFAST | C9: 75
A10: SAN BENEDETTO DEL TRONTO | B10: ALBERGHI | C10: 73
A11: URBINO | B11: BED & BREAKFAST | C11: 72
A12: FANO | B12: BED & BREAKFAST | C12: 64
A13: GROTTAMMARE | B13: STABILIMENTI BALNEARI | C13: 62
... A1197: TORRE SAN PATRIZIO | B1197: BED & BREAKFAST | C1197: 1

Sheet ESERCIZIO 4-5
A2: MASCHERA DI RICERCA - CONTEGGI
B4: RICERCA STRUTTURA
B6: NOME STRUTTURA | C6: Leon D'Oro
B7: CITTA' | C7: =IF( _xlfn.XLOOKUP($C$6,MergePrezzoMedio[Denominazione],MergePrezzoMedio[Città],"Non trovata")="", "Non trovata", _xlfn.XLOOKUP($C$6,MergePrezzoMedio[Denominazione],MergePrezzoMedio[Città],"Non trovata") ) -> ACQUALAGNA
B8: INDIRIZZO | C8: =_xlfn.XLOOKUP($C$6,MergePrezzoMedio[Denominazione],MergePrezzoMedio[Indirizzo],"Non trovata") -> Via Flaminia 213
B9: EMAIL | C9: =IF( _xlfn.XLOOKUP($C$6,MergePrezzoMedio[Denominazione],MergePrezzoMedio[Indirizzo di posta elettronica],"Non trovata")="", "Non trovata", _xlfn.XLOOKUP($C$6,MergePrezzoMedio[Denominazione],MergePrezzoMedio[Indirizzo di posta elettronica],"Non trovata") ) -> Non trovata
B10: INDIRIZZO WEB | C10: =IF( _xlfn.XLOOKUP($C$6,MergePrezzoMedio[Denominazione],MergePrezzoMedio[Indirizzo internet],"Non trovata")="", "Non trovata", _xlfn.XLOOKUP($C$6,MergePrezzoMedio[Denominazione],MergePrezzoMedio[Indirizzo internet],"Non trovata") ) -> Non trovata
B11: Numero totale strutture | C11: =COUNTA(MergePrezzoMedio[Denominazione]) -> 6258
B12: Numero strutture per LOCALITA' | C12: =COUNTIF(MergePrezzoMedio[Città],$C$7) -> 25

Sheet ESERCIZIO 6
A2: CLASSIFICA E FILTRA
A4: CATEGORIA STRUTTURA | B4: NR STRUTTURE | D4: CATEGORIA STRUTTURA | E4: NR STRUTTURE
A5: {=_xlfn.UNIQUE(MergePrezzoMedio[Categoria])} -> TURISMO RURALE | B5: =COUNTIF(MergePrezzoMedio[Categoria],'ESERCIZIO 6'!$A5) -> 304 | D5: {=_xlfn.SORTBY(A5:B19,B5:B19,-1)} -> BED & BREAKFAST | E5: 1809
A6: ALTRI ALLOGGI PRIVATI | B6: =COUNTIF(MergePrezzoMedio[Categoria],'ESERCIZIO 6'!$A6) -> 721 | D6: STABILIMENTI BALNEARI | E6: 850
A7: ALBERGHI | B7: =COUNTIF(MergePrezzoMedio[Categoria],'ESERCIZIO 6'!$A7) -> 814 | D7: ALLOGGI AGRITURISTICI | E7: 830
A8: BED & BREAKFAST | B8: =COUNTIF(MergePrezzoMedio[Categoria],'ESERCIZIO 6'!$A8) -> 1809 | D8: ALBERGHI | E8: 814
A9: ALLOGGI AGRITURISTICI | B9: =COUNTIF(MergePrezzoMedio[Categoria],'ESERCIZIO 6'!$A9) -> 830 | D9: ALTRI ALLOGGI PRIVATI | E9: 721
A10: ALLOGGI IN AFFITTO | B10: =COUNTIF(MergePrezzoMedio[Categoria],'ESERCIZIO 6'!$A10) -> 541 | D10: ALLOGGI IN AFFITTO | E10: 541
A11: AREE DI SOSTA (PLEIN AIR) | B11: =COUNTIF(MergePrezzoMedio[Categoria],'ESERCIZIO 6'!$A11) -> 86 | D11: TURISMO RURALE | E11: 304
A12: OSTELLI PER LA GIOVENTU' | B12: =COUNTIF(MergePrezzoMedio[Categoria],'ESERCIZIO 6'!$A12) -> 30 | D12: CAMPEGGI | E12: 93
A13: CASE PER FERIE | B13: =COUNTIF(MergePrezzoMedio[Categoria],'ESERCIZIO 6'!$A13) -> 82 | D13: AREE DI SOSTA (PLEIN AIR) | E13: 86
A14: RIFUGI | B14: =COUNTIF(MergePrezzoMedio[Categoria],'ESERCIZIO 6'!$A14) -> 16 | D14: CASE PER FERIE | E14: 82
A15: RESIDENZE TURISTICO ALBERGHIERE | B15: =COUNTIF(MergePrezzoMedio[Categoria],'ESERCIZIO 6'!$A15) -> 52 | D15: RESIDENZE TURISTICO ALBERGHIERE | E15: 52
A16: CAMPEGGI | B16: =COUNTIF(MergePrezzoMedio[Categoria],'ESERCIZIO 6'!$A16) -> 93 | D16: OSTELLI PER LA GIOVENTU' | E16: 30
A17: STABILIMENTI BALNEARI | B17: =COUNTIF(MergePrezzoMedio[Categoria],'ESERCIZIO 6'!$A17) -> 850 | D17: VILLAGGI TURISTICI | E17: 17
... A19: VILLAGGI TURISTICI | B19: =COUNTIF(MergePrezzoMedio[Categoria],'ESERCIZIO 6'!$A19) -> 17 | D19: ALTRI ESERCIZI RICETTIVI | E19: 13
A22: CITTA' SCELTA: | B22: PETRITOLI
A24: {=_xlfn._xlws.FILTER(MergePrezzoMedio[],MergePrezzoMedio[Città]=$B$22,"Non trovata")} -> ALBERGHI | B24: Roma | C24: Contrada Sant' Antonio 10 | D24: PETRITOLI | E24: 90 | F24: PETRITOLI | G24: www.albergoroma.it | H24: fulvital@tin.it
A25: BED & BREAKFAST | B25: B&B Mare E Monti | C25: Contrada Agelli 52 | D25: PETRITOLI | E25: 90 | F25: PETRITOLI | G25: www.mareemontimarche.com | H25: info@mareemontimarche.com
A26: ALLOGGI AGRITURISTICI | B26: M.E.S. - Azienda Agricola Di Cicchese Paola | C26: Contrada San Savino 57 | D26: PETRITOLI | E26: 90 | F26: PETRITOLI | G26: www.agribiomes.it | H26: info@agribiomes.it
A27: ALLOGGI AGRITURISTICI | B27: Lo Scoiattolo | C27: Contrada Maltignano 9 | D27: PETRITOLI | E27: 90 | F27: PETRITOLI | G27: www.agriturismoloscoiattolo.it | H27: agriturismoloscoiattolo@alice.it
A28: ALLOGGI AGRITURISTICI | B28: Parco Galeano | D28: PETRITOLI | E28: 90 | G28: www.parcogaleano.it | H28: info@parcogaleano.it
A29: BED & BREAKFAST | B29: B&B Parisi Rosaria | C29: C.Da Solagna 1 | D29: PETRITOLI | E29: 90 | F29: MOREGNANO | H29: info.raggiodisole@hotmail.com
A30: BED & BREAKFAST | B30: B&B Casa Cormar | C30: Contrada Sant'Antonio 6 | D30: PETRITOLI | E30: 90 | G30: http://www.casacormar.com/it/benvenuti | H30: info@casacormar.com
A31: BED & BREAKFAST | B31: B&B Elena Monaldi | C31: Via Sant'Antonio 122 | D31: PETRITOLI | E31: 90 | F31: PETRITOLI | G31: www.bluemoonresort.it | H31: elena.monaldi@gmail.com
A32: BED & BREAKFAST | B32: B&B Villa Toccamona Petritoli | C32: C.Da San Marziale 5 | D32: PETRITOLI | E32: 90 | H32: lambertosantoni@gmail.com
A33: ALTRI ALLOGGI PRIVATI | B33: Casa Iris | D33: PETRITOLI | E33: 90 | H33: diegomorellidm@libero.it
A34: BED & BREAKFAST | B34: B&B Capanna Margherita | C34: Contrada Montoro 18 | D34: PETRITOLI | E34: 90 | F34: PETRITOLI | H34: reinhold@cab-bike.com
A35: BED & BREAKFAST | B35: B&B La Scentella | C35: Contrada Sant' Antonio 4 | D35: PETRITOLI | E35: 90 | F35: PETRITOLI | G35: www.scentella.it | H35: info@scentella.it
A36: ALLOGGI AGRITURISTICI | B36: Agriturismo Serena | C36: Contrada Contro 11 | D36: PETRITOLI | E36: 90 | F36: PETRITOLI | G36: www.agriturismoserena.it | H36: info@agriturismoserena.it
A37: BED & BREAKFAST | B37: B&B Foglini Livia | C37: Contrada San Savino 51 | D37: PETRITOLI | E37: 90 | F37: PETRITOLI | G37: www.ilbiologicodilivia.com | H37: foam.bio@gmail.com
A38: BED & BREAKFAST | B38: B&B Bates Geoffrey | C38: Largo Lucentini 5 | D38: PETRITOLI | E38: 90 | F38: PETRITOLI
A39: ALLOGGI IN AFFITTO | B39: Affittacamere Vitali Fulvio | C39: Largo Giacomo Leopardi 26 | D39: PETRITOLI | E39: 90 | F39: PETRITOLI
A40: ALBERGHI | B40: Dipendenza Hotel Roma | C40: Largo Giacomo Leopardi 26 | D40: PETRITOLI | E40: 90 | F40: PETRITOLI | G40: www.albergoroma.it | H40: fulvital@tin.it
A41: BED & BREAKFAST | B41: B&B Regina Margherita | C41: Via Tornabuoni 27 | D41: PETRITOLI | E41: 90 | H41: andrea.mars92@gmail.com

Sheet ESERCIZIO 7-8-9
A2: INDICI
A4: MEDIA | B4: =AVERAGE(MergePrezzoMedio[PREZZO MEDIO]) -> 73.711569
A5: MEDIANA | B5: =MEDIAN(MergePrezzoMedio[PREZZO MEDIO]) -> 75
A6: MODA | B6: =MODE(MergePrezzoMedio[PREZZO MEDIO]) -> 59
A7: VARIANZA | B7: =_xlfn.VAR.P(MergePrezzoMedio[PREZZO MEDIO]) -> 746.16561
A8: DEVIAZIONE STANDARD | B8: =_xlfn.STDEV.P(MergePrezzoMedio[PREZZO MEDIO]) -> 27.316032
A9: PRIMO QUARTILE | B9: =_xlfn.QUARTILE.INC(MergePrezzoMedio[],1) -> 51
A10: TERZO QUARTILE | B10: =_xlfn.QUARTILE.INC(MergePrezzoMedio[],3) -> 93
A11: IQR | B11: =B10-B9 -> 42
A13: Media (73,71 €) e mediana (75 €) sono molto vicine; pertanto la distribuzione dei prezzi medi può essere considerata sostanzialmente simmetrica, con una lieve tendenza all'asimmetria negativa
A16: DISTRIBUZIONE
A18: Classe (€) | B18: Frequenza assoluta | C18: Frequenza relativa | D18: Frequenza %
A19: 30–49 | B19: =COUNTIFS(MergePrezzoMedio[PREZZO MEDIO],">=30",MergePrezzoMedio[PREZZO MEDIO],"<=49") -> 1452 | C19: =$B19/$B$24 -> 0.23202301 | D19: =$C19 -> 0.23202301
A20: 50–69 | B20: =COUNTIFS(MergePrezzoMedio[PREZZO MEDIO],">=50",MergePrezzoMedio[PREZZO MEDIO],"<=69") -> 1389 | C20: =$B20/$B$24 -> 0.2219559 | D20: =$C20 -> 0.2219559
A21: 70–89 | B21: =COUNTIFS(MergePrezzoMedio[PREZZO MEDIO],">=70",MergePrezzoMedio[PREZZO MEDIO],"<=89") -> 1748 | C21: =$B21/$B$24 -> 0.27932247 | D21: =$C21 -> 0.27932247
A22: 90–109 | B22: =COUNTIFS(MergePrezzoMedio[PREZZO MEDIO],">=90",MergePrezzoMedio[PREZZO MEDIO],"<=109") -> 808 | C22: =$B22/$B$24 -> 0.12911473 | D22: =$C22 -> 0.12911473
A23: 110–129 | B23: =COUNTIFS(MergePrezzoMedio[PREZZO MEDIO],">=110",MergePrezzoMedio[PREZZO MEDIO],"<=129") -> 861 | C23: =$B23/$B$24 -> 0.13758389 | D23: =$C23 -> 0.13758389
A24: Totale | B24: =SUM(B19:B23) -> 6258 | C24: 1 | D24: =SUM(D19:D23) -> 1
A26: La distribuzione dei prezzi medi è concentrata principalmente nella classe 70–89 €, che rappresenta la classe modale con 1.748 osservazioni (28%). Le classi 30–49 € e 50–69 € presentano frequenze simili (23% e 22%), mentre le classi con prezzi superiori ai 90 € risultano meno frequenti.
A29: OUTLIER
A31: LIM. INF. | B31: =B9-1.5*B11 -> -12
A32: LIM. SUP. | B32: =B10+1.5*B11 -> 156
A34: Applicando la regola dell'IQR, i limiti di Tukey risultano pari a -12 € e 156 €. Poiché tutti i prezzi medi del dataset sono compresi tra 30 € e 120 €, non sono presenti outlier. Di conseguenza, la deviazione standard rimane invariata.

Sheet ESERCIZIO 10-11-12
A2: PROBABILITA' DAI CONTEGGI
A4: NR. TOT ALBERGHI | B4: =COUNTIF(MergePrezzoMedio[Categoria],"ALBERGHI") -> 814
A5: NR. TOT B&B | B5: =COUNTIF(MergePrezzoMedio[Categoria],"BED & BREAKFAST") -> 1809
A6: NR. TOT STRUTTURE | B6: =COUNTA(MergePrezzoMedio[Categoria]) -> 6258
A8: PRIMA RICHIESTA: Qual è la probabilità che una struttura sia un ALBERGO oppure un BED & BREAKFAST?
A10: Essendo due eventi incompatibili, vale la formula:
A12: P(A∪B) | B12: =(B4/B6)+(B5/B6) -> 0.4191435 | C12: =B12 -> 0.4191435
A14: SECONDA RICHIESTA: Estraendo due indipendenti, qual è la probabilità che siano entrambi alberghi?
A16: Essendo eventi indipendenti, vale la formula:
C18: frazione | D18: %
A19: primo tiro estrae alberghi | B19: P(A) | C19: =B4/B6 -> 0.13007351 | D19: =C19 -> 0.13007351
A20: secondo tiro estrae alberghi | B20: P(B) | C20: =B4/B6 -> 0.13007351 | D20: =C20 -> 0.13007351
B21: P(A∩B) | C21: =C19*C20 -> 0.016919117 | D21: =C21 -> 0.016919117
A25: REGOLA 68-95-99,7
A27: MEDIA | B27: ='ESERCIZIO 7-8-9'!B4 -> 73.711569
A28: DEVIAZIONE STANDARD | B28: ='ESERCIZIO 7-8-9'!B8 -> 27.316032
A29: LIM. INF. INTERVALLO | B29: =B27-B28 -> 46.395537
A30: LIM. SUP. INTERVALLO | B30: =B27+B28 -> 101.0276
A32: pertanto il prezzo: | B32: 46,40<= prezzo <= 101,03
A34: Considerando che i prezzi medi seguano una distribuzione normale, circa il 68% delle città presenta un prezzo medio compreso tra 46,39 € e 101,03 €, cioè entro una deviazione standard dalla media.
A37: Z-SCORE
A39: CITTA' SCELTA: | B39: SMERILLO
A41: PREZZO MEDIO | B41: =VLOOKUP(B39,MergePrezzoMedio[[Città]:[PREZZO MEDIO]],2,0) -> 113
A42: MEDIA | B42: =B27 -> 73.711569
A43: DEVIAZIONE STANDARD | B43: =B28 -> 27.316032
A44: Z-SCORE | B44: =STANDARDIZE(B41,B42,B43) -> 1.438292
A46: La città di Smerillo presenta un prezzo medio di 113 €, superiore alla media del campione (73,71 €). Lo Z-score è pari a 1,44, il che significa che il prezzo medio di Smerillo si trova a 1,44 deviazioni standard al di sopra della media.
A48: calcolo la "probabilità di osservare un prezzo inferiore" | C48: =_xlfn.NORM.S.DIST(B44,TRUE) -> 0.92482439
A50: Applicando la funzione DISTRIB.NORM.ST(Z;VERO) allo Z-score di 1,44, si ottiene una probabilità pari a 0,9251 (92,51%). Ciò significa che, assumendo una distribuzione normale dei prezzi medi, circa il 92,51% delle città presenta un prezzo medio inferiore o uguale a quello di Smerillo

Sheet ESERCIZIO 13-14
A1: Città | B1: PREZZO MEDIO
A2: {=_xlfn.UNIQUE(MergePrezzoMedio[Città],FALSE,FALSE)} -> URBINO | B2: =VLOOKUP(A2,MergePrezzoMedio[[Città]:[PREZZO MEDIO]],2,0) -> 31 | E2: INTERVALLO DI CONFIDENZA
A3: ACQUALAGNA | B3: =VLOOKUP(A3,MergePrezzoMedio[[Città]:[PREZZO MEDIO]],2,0) -> 75
A4: APECCHIO | B4: =VLOOKUP(A4,MergePrezzoMedio[[Città]:[PREZZO MEDIO]],2,0) -> 77 | E4: MEDIA | F4: =AVERAGE('ESERCIZIO 13-14'!B2:B235) -> 73.5
A5: AUDITORE | B5: =VLOOKUP(A5,MergePrezzoMedio[[Città]:[PREZZO MEDIO]],2,0) -> 93 | E5: DEVIAZIONE STANDARD | F5: =_xlfn.STDEV.P('ESERCIZIO 13-14'!B2:B235) -> 27.460189
A6: BARCHI | B6: =VLOOKUP(A6,MergePrezzoMedio[[Città]:[PREZZO MEDIO]],2,0) -> 83 | E6: DIM. CAMPIONE | F6: =COUNTA(_xlfn.ANCHORARRAY('ESERCIZIO 13-14'!A2)) -> 234
A7: BELFORTE ALL'ISAURO | B7: =VLOOKUP(A7,MergePrezzoMedio[[Città]:[PREZZO MEDIO]],2,0) -> 49 | E7: CONFIDENZA (%) | F7: 0.95
A8: BORGO PACE | B8: =VLOOKUP(A8,MergePrezzoMedio[[Città]:[PREZZO MEDIO]],2,0) -> 58
A9: CAGLI | B9: =VLOOKUP(A9,MergePrezzoMedio[[Città]:[PREZZO MEDIO]],2,0) -> 64 | E9: ALPHA | F9: =1-F7 -> 0.05
A10: CANTIANO | B10: =VLOOKUP(A10,MergePrezzoMedio[[Città]:[PREZZO MEDIO]],2,0) -> 106 | E10: MARGINE ERRORE | F10: =_xlfn.CONFIDENCE.NORM(F9,F5,F6) -> 3.5183876
A11: CARPEGNA | B11: =VLOOKUP(A11,MergePrezzoMedio[[Città]:[PREZZO MEDIO]],2,0) -> 118 | E11: LIM. INF. | F11: =F4-F10 -> 69.981612
A12: CARTOCETO | B12: =VLOOKUP(A12,MergePrezzoMedio[[Città]:[PREZZO MEDIO]],2,0) -> 36 | E12: LIM. SUP. | F12: =F4+F10 -> 77.018388
A13: FANO | B13: =VLOOKUP(A13,MergePrezzoMedio[[Città]:[PREZZO MEDIO]],2,0) -> 120
A14: FERMIGNANO | B14: =VLOOKUP(A14,MergePrezzoMedio[[Città]:[PREZZO MEDIO]],2,0) -> 88
A15: FOSSOMBRONE | B15: =VLOOKUP(A15,MergePrezzoMedio[[Città]:[PREZZO MEDIO]],2,0) -> 66 | E15: EFFETTO DI N
A16: FRATTE ROSA | B16: =VLOOKUP(A16,MergePrezzoMedio[[Città]:[PREZZO MEDIO]],2,0) -> 119
A17: FRONTINO | B17: =VLOOKUP(A17,MergePrezzoMedio[[Città]:[PREZZO MEDIO]],2,0) -> 52 | E17: MEDIA | F17: =F4 -> 73.5
A18: FRONTONE | B18: =VLOOKUP(A18,MergePrezzoMedio[[Città]:[PREZZO MEDIO]],2,0) -> 75 | E18: DEVIAZIONE STANDARD | F18: =F5 -> 27.460189
A19: GABICCE MARE | B19: =VLOOKUP(A19,MergePrezzoMedio[[Città]:[PREZZO MEDIO]],2,0) -> 112 | E19: DIM. CAMPIONE | F19: =COUNTA(_xlfn.ANCHORARRAY('ESERCIZIO 13-14'!A2)) -> 234
A20: GRADARA | B20: =VLOOKUP(A20,MergePrezzoMedio[[Città]:[PREZZO MEDIO]],2,0) -> 87 | E20: CONFIDENZA (%) | F20: 0.9
A21: ISOLA DEL PIANO | B21: =VLOOKUP(A21,MergePrezzoMedio[[Città]:[PREZZO MEDIO]],2,0) -> 46
A22: LUNANO | B22: =VLOOKUP(A22,MergePrezzoMedio[[Città]:[PREZZO MEDIO]],2,0) -> 36 | E22: ALPHA | F22: =1-F20 -> 0.1
A23: MACERATA FELTRIA | B23: =VLOOKUP(A23,MergePrezzoMedio[[Città]:[PREZZO MEDIO]],2,0) -> 32 | E23: MARGINE ERRORE | F23: =_xlfn.CONFIDENCE.NORM(F22,F18,F19) -> 2.9527239
A24: MERCATELLO SUL METAURO | B24: =VLOOKUP(A24,MergePrezzoMedio[[Città]:[PREZZO MEDIO]],2,0) -> 85 | E24: LIM. INF. | F24: =F17-F23 -> 70.547276
A25: MERCATINO CONCA | B25: =VLOOKUP(A25,MergePrezzoMedio[[Città]:[PREZZO MEDIO]],2,0) -> 120 | E25: LIM. SUP. | F25: =F17+F23 -> 76.452724
A26: MOMBAROCCIO | B26: =VLOOKUP(A26,MergePrezzoMedio[[Città]:[PREZZO MEDIO]],2,0) -> 39
A27: MONDAVIO | B27: =VLOOKUP(A27,MergePrezzoMedio[[Città]:[PREZZO MEDIO]],2,0) -> 116 | E27: MEDIA | F27: =F17 -> 73.5
A28: MONDOLFO | B28: =VLOOKUP(A28,MergePrezzoMedio[[Città]:[PREZZO MEDIO]],2,0) -> 64 | E28: DEVIAZIONE STANDARD | F28: =F18 -> 27.460189
A29: MONTECALVO IN FOGLIA | B29: =VLOOKUP(A29,MergePrezzoMedio[[Città]:[PREZZO MEDIO]],2,0) -> 46 | E29: DIM. CAMPIONE | F29: =COUNTA(_xlfn.ANCHORARRAY('ESERCIZIO 13-14'!A2)) -> 234
A30: MONTE CERIGNONE | B30: =VLOOKUP(A30,MergePrezzoMedio[[Città]:[PREZZO MEDIO]],2,0) -> 78 | E30: CONFIDENZA (%) | F30: 0.99
A31: MONTECICCARDO | B31: =VLOOKUP(A31,MergePrezzoMedio[[Città]:[PREZZO MEDIO]],2,0) -> 48
A32: MONTECOPIOLO | B32: =VLOOKUP(A32,MergePrezzoMedio[[Città]:[PREZZO MEDIO]],2,0) -> 51 | E32: ALPHA | F32: =1-F30 -> 0.01
A33: MONTEFELCINO | B33: =VLOOKUP(A33,MergePrezzoMedio[[Città]:[PREZZO MEDIO]],2,0) -> 61 | E33: MARGINE ERRORE | F33: =_xlfn.CONFIDENCE.NORM(F32,F28,F29) -> 4.6239451
A34: MONTE GRIMANO TERME | B34: =VLOOKUP(A34,MergePrezzoMedio[[Città]:[PREZZO MEDIO]],2,0) -> 107 | E34: LIM. INF. | F34: =F27-F33 -> 68.876055
A35: MONTELABBATE | B35: =VLOOKUP(A35,MergePrezzoMedio[[Città]:[PREZZO MEDIO]],2,0) -> 49 | E35: LIM. SUP. | F35: =F27+F33 -> 78.123945
A36: MONTEMAGGIORE AL METAURO | B36: =VLOOKUP(A36,MergePrezzoMedio[[Città]:[PREZZO MEDIO]],2,0) -> 120
A37: MONTE PORZIO | B37: =VLOOKUP(A37,MergePrezzoMedio[[Città]:[PREZZO MEDIO]],2,0) -> 119 | E37: All'aumentare del livello di confidenza aumenta anche il margine di errore e, di conseguenza, l'intervallo di confidenza diventa più ampio. L'intervallo al 90% è il più ristretto, quello al 95% è intermedio e quello al 99% è il più ampio.
A38: ORCIANO DI PESARO | B38: =VLOOKUP(A38,MergePrezzoMedio[[Città]:[PREZZO MEDIO]],2,0) -> 85
A39: PEGLIO | B39: =VLOOKUP(A39,MergePrezzoMedio[[Città]:[PREZZO MEDIO]],2,0) -> 109 | E39: Aumentando la numerosità del campione, il margine di errore si riduce. Se il campione quadruplicasse, il margine di errore si dimezzerebbe e l'intervallo di confidenza diventerebbe più stretto, rendendo la stima del prezzo medio più accurata.
A40: PERGOLA | B40: =VLOOKUP(A40,MergePrezzoMedio[[Città]:[PREZZO MEDIO]],2,0) -> 35
A41: PESARO | B41: =VLOOKUP(A41,MergePrezzoMedio[[Città]:[PREZZO MEDIO]],2,0) -> 86
A42: PETRIANO | B42: =VLOOKUP(A42,MergePrezzoMedio[[Città]:[PREZZO MEDIO]],2,0) -> 78
A43: PIAGGE | B43: =VLOOKUP(A43,MergePrezzoMedio[[Città]:[PREZZO MEDIO]],2,0) -> 39
A44: PIANDIMELETO | B44: =VLOOKUP(A44,MergePrezzoMedio[[Città]:[PREZZO MEDIO]],2,0) -> 58
A45: PIETRARUBBIA | B45: =VLOOKUP(A45,MergePrezzoMedio[[Città]:[PREZZO MEDIO]],2,0) -> 119
A46: PIOBBICO | B46: =VLOOKUP(A46,MergePrezzoMedio[[Città]:[PREZZO MEDIO]],2,0) -> 117
A47: SALTARA | B47: =VLOOKUP(A47,MergePrezzoMedio[[Città]:[PREZZO MEDIO]],2,0) -> 56
A48: SAN COSTANZO | B48: =VLOOKUP(A48,MergePrezzoMedio[[Città]:[PREZZO MEDIO]],2,0) -> 78
A49: SAN GIORGIO DI PESARO | B49: =VLOOKUP(A49,MergePrezzoMedio[[Città]:[PREZZO MEDIO]],2,0) -> 71
A50: SAN LORENZO IN CAMPO | B50: =VLOOKUP(A50,MergePrezzoMedio[[Città]:[PREZZO MEDIO]],2,0) -> 95
A51: SANT'ANGELO IN VADO | B51: =VLOOKUP(A51,MergePrezzoMedio[[Città]:[PREZZO MEDIO]],2,0) -> 33
... A235: TORRE SAN PATRIZIO | B235: =VLOOKUP(A235,MergePrezzoMedio[[Città]:[PREZZO MEDIO]],2,0) -> 50

Sheet ESERCIZIO 15
A1: ALBERGHI | B1: AGRITURISMI
A2: 75 | B2: 75 | E2: CONFRONTO TRA GRUPPI
A3: 75 | B3: 75
A4: 75 | B4: 75 | E4: IPOTESI NULLA (H0) | F4: La differenza tra il prezzo medio degli alberghi e quello degli agriturismi non è statisticamente significativa
A5: 75 | B5: 75 | E5: IPOTESI ALTERNATIVA (H1) | F5: La differenza tra il prezzo medio degli alberghi e quello degli agriturismi è statisticamente significativa
A6: 75 | B6: 77
A7: 75 | B7: 77 | E7: ALPHA | F7: 0.05
A8: 77 | B8: 77 | E8: P-VALUE | F8: =TTEST(Tabella1[ALBERGHI],Tabella2[AGRITURISMI],2,3) -> 3.0186045e-10
A9: 77 | B9: 77
A10: 93 | B10: 77 | E10: poiché p<α allora rifiuto H0
A11: 93 | B11: 77 | E11: Poiché il p-value è inferiore al livello di significatività α, si rifiuta l'ipotesi nulla (H₀). Si conclude quindi che la differenza tra il prezzo medio degli alberghi e quello degli agriturismi è statisticamente significativa.
A12: 58 | B12: 77
A13: 58 | B13: 77
A14: 58 | B14: 77
A15: 64 | B15: 77
A16: 64 | B16: 77
A17: 106 | B17: 77
A18: 106 | B18: 83
A19: 118 | B19: 83
A20: 118 | B20: 49
A21: 118 | B21: 58
A22: 118 | B22: 58
A23: 120 | B23: 58
... A815: 83 | B815: 112
B816: 54
B817: 54
B818: 54
B819: 54
B820: 54
B821: 54
B822: 54
B823: 54
B824: 83
B825: 113
B826: 113
B827: 113
... B831: 50

Sheet ESERCIZIO 16-17
A1: Città | B1: Totale Categoria | C1: PREZZO MEDIO
A2: ACQUALAGNA | B2: 25 | C2: =VLOOKUP(A2,MergePrezzoMedio[[Città]:[PREZZO MEDIO]],2,0) -> 75 | G2: CORRELAZIONE
A3: ACQUASANTA TERME | B3: 26 | C3: =VLOOKUP(A3,MergePrezzoMedio[[Città]:[PREZZO MEDIO]],2,0) -> 98
A4: ACQUAVIVA PICENA | B4: 19 | C4: =VLOOKUP(A4,MergePrezzoMedio[[Città]:[PREZZO MEDIO]],2,0) -> 61 | G4: COVARIANZA | H4: =_xlfn.COVARIANCE.S(Tabella6[Totale Categoria],Tabella6[PREZZO MEDIO]) -> 5.6824034
A5: AGUGLIANO | B5: 5 | C5: =VLOOKUP(A5,MergePrezzoMedio[[Città]:[PREZZO MEDIO]],2,0) -> 81 | G5: COEFF. CORRELAZIONE | H5: =CORREL(Tabella6[Totale Categoria],Tabella6[PREZZO MEDIO]) -> 0.0040492349
A6: ALTIDONA | B6: 14 | C6: =VLOOKUP(A6,MergePrezzoMedio[[Città]:[PREZZO MEDIO]],2,0) -> 71
A7: AMANDOLA | B7: 27 | C7: =VLOOKUP(A7,MergePrezzoMedio[[Città]:[PREZZO MEDIO]],2,0) -> 84 | F7: la covarianza è positiva ed indica la tendenza delle due variabili a variare insieme
A8: ANCONA | B8: 184 | C8: =VLOOKUP(A8,MergePrezzoMedio[[Città]:[PREZZO MEDIO]],2,0) -> 34 | F8: il coefficiente di correlazione è positivo ed è estremamente vicino allo zero, questo indica che non esiste una relazione significativa tra il numero di strutture presenti in una città e il relativo prezzo medio
A9: APECCHIO | B9: 31 | C9: =VLOOKUP(A9,MergePrezzoMedio[[Città]:[PREZZO MEDIO]],2,0) -> 77
A10: APIRO | B10: 10 | C10: =VLOOKUP(A10,MergePrezzoMedio[[Città]:[PREZZO MEDIO]],2,0) -> 100
A11: APPIGNANO | B11: 7 | C11: =VLOOKUP(A11,MergePrezzoMedio[[Città]:[PREZZO MEDIO]],2,0) -> 50 | G11: CORRELAZIONE
A12: APPIGNANO DEL TRONTO | B12: 4 | C12: =VLOOKUP(A12,MergePrezzoMedio[[Città]:[PREZZO MEDIO]],2,0) -> 86
A13: ARCEVIA | B13: 63 | C13: =VLOOKUP(A13,MergePrezzoMedio[[Città]:[PREZZO MEDIO]],2,0) -> 49
A14: ARQUATA DEL TRONTO | B14: 22 | C14: =VLOOKUP(A14,MergePrezzoMedio[[Città]:[PREZZO MEDIO]],2,0) -> 31
A15: ASCOLI PICENO | B15: 161 | C15: =VLOOKUP(A15,MergePrezzoMedio[[Città]:[PREZZO MEDIO]],2,0) -> 100
A16: AUDITORE | B16: 7 | C16: =VLOOKUP(A16,MergePrezzoMedio[[Città]:[PREZZO MEDIO]],2,0) -> 93
A17: BARCHI | B17: 8 | C17: =VLOOKUP(A17,MergePrezzoMedio[[Città]:[PREZZO MEDIO]],2,0) -> 83
A18: BELFORTE ALL'ISAURO | B18: 3 | C18: =VLOOKUP(A18,MergePrezzoMedio[[Città]:[PREZZO MEDIO]],2,0) -> 49
A19: BELFORTE DEL CHIENTI | B19: 10 | C19: =VLOOKUP(A19,MergePrezzoMedio[[Città]:[PREZZO MEDIO]],2,0) -> 44
A20: BELMONTE PICENO | B20: 6 | C20: =VLOOKUP(A20,MergePrezzoMedio[[Città]:[PREZZO MEDIO]],2,0) -> 75
A21: BELVEDERE OSTRENSE | B21: 8 | C21: =VLOOKUP(A21,MergePrezzoMedio[[Città]:[PREZZO MEDIO]],2,0) -> 52
A22: BOLOGNOLA | B22: 4 | C22: =VLOOKUP(A22,MergePrezzoMedio[[Città]:[PREZZO MEDIO]],2,0) -> 42
A23: BORGO PACE | B23: 15 | C23: =VLOOKUP(A23,MergePrezzoMedio[[Città]:[PREZZO MEDIO]],2,0) -> 58
... A235: VISSO | B235: 20 | C235: =VLOOKUP(A235,MergePrezzoMedio[[Città]:[PREZZO MEDIO]],2,0) -> 36

Sheet ESERCIZIO 17B
A1: OUTPUT RIEPILOGO
A3: Statistica della regressione
A4: R multiplo | B4: 0.0040492349
A5: R al quadrato | B5: 1.6396304e-05
A6: R al quadrato corretto | B6: -0.0042938779
A7: Errore standard | B7: 27.578072
A8: Osservazioni | B8: 234
A10: ANALISI VARIANZA
B11: gdl | C11: SQ | D11: MQ | E11: F | F11: Significatività F
A12: Regressione | B12: 1 | C12: 2.893136 | D12: 2.893136 | E12: 0.0038040048 | F12: 0.95087346
A13: Residuo | B13: 232 | C13: 176447.61 | D13: 760.55003
A14: Totale | B14: 233 | C14: 176450.5
B16: Coefficienti | C16: Errore standard | D16: Stat t | E16: Valore di significatività | F16: Inferiore 95% | G16: Superiore 95% | H16: Inferiore 95,0% | I16: Superiore 95,0%
A17: Intercetta | B17: 73.441561 | C17: 2.0366574 | D17: 36.05985 | E17: 4.4704553e-97 | F17: 69.428853 | G17: 77.454269 | H17: 69.428853 | I17: 77.454269
A18: Totale Categoria | B18: 0.002185148 | C18: 0.035429117 | D18: 0.061676615 | E18: 0.95087346 | F18: -0.067618784 | G18: 0.07198908 | H18: -0.067618784 | I18: 0.07198908
A21: R al quadrato | B21: 1.6396304e-05 | C21: Il coefficiente di determinazione è molto piccolo e tende a zero. Ciò indica che il numero di strutture spiega una quota praticamente nulla della variabilità del prezzo medio.
A23: Valore di significatività
A24: 0.95087346
B25: il p-value e la Significatività F sono entrambi maggiori del livello di significatività (α = 0,05). Pertanto, non si rifiuta l'ipotesi nulla (H₀) e il modello di regressione non risulta statisticamente significativo.
A26: Significatività F
A27: 0.95087346

Sheet ESERCIZIO 18
A2: PREVISIONE E LIMITI
A4: considerata l'equazione della retta dell'esercizio 17
A6: y = 0,0022x + 73,442
A8: scelgo una città con 150 strutture, quindi l'equazione diventa:
A10: y = 0,0022 * 150 + 73,442 | B10: ovvero: | C10: y | D10: =0.0022*150+73.442 -> 73.772
A13: La stima ottenuta è poco affidabile, poiché il modello di regressione non è statisticamente significativo. Inoltre, il coefficiente di determinazione (R²) è molto vicino a zero, indicando che il numero di strutture spiega una quota praticamente nulla della variabilità del prezzo medio. Si conclude quindi che la correlazione tra le variabili è estremamente debole
